{"v":"5.12.1","fr":25,"ip":0,"op":101,"w":360,"h":780,"nm":"POINT 482","ddd":0,"assets":[{"id":"comp_0","nm":"Tooltip message_1","fr":25,"layers":[{"ddd":0,"ind":1,"ty":3,"nm":"NULL","sr":1,"ks":{"o":{"a":0,"k":0,"ix":11},"r":{"a":0,"k":0,"ix":10},"p":{"a":0,"k":[204.5,18,0],"ix":2,"l":2},"a":{"a":0,"k":[50,50,0],"ix":1,"l":2},"s":{"a":1,"k":[{"i":{"x":[0.667,0.667,0.667],"y":[1,1,1]},"o":{"x":[0.333,0.333,0.333],"y":[0,0,0]},"t":0,"s":[0,0,100]},{"i":{"x":[0.667,0.667,0.667],"y":[1,1,1]},"o":{"x":[0.333,0.333,0.333],"y":[0,0,0]},"t":7,"s":[25,25,100]},{"t":10,"s":[20,20,100]}],"ix":6,"l":2}},"ao":0,"ip":0,"op":1694,"st":0,"bm":0},{"ddd":0,"ind":2,"ty":4,"nm":"Layer 5 Outlines","parent":1,"sr":1,"ks":{"o":{"a":0,"k":100,"ix":11},"r":{"a":1,"k":[{"i":{"x":[0.667],"y":[1]},"o":{"x":[0.333],"y":[0]},"t":0,"s":[0]},{"i":{"x":[0.667],"y":[1]},"o":{"x":[0.333],"y":[0]},"t":5.25,"s":[20]},{"i":{"x":[0.667],"y":[1]},"o":{"x":[0.333],"y":[0]},"t":10.5,"s":[-11]},{"i":{"x":[0.667],"y":[1]},"o":{"x":[0.333],"y":[0]},"t":15.75,"s":[20]},{"t":21,"s":[0]}],"ix":10},"p":{"a":0,"k":[-560.15,208.569,0],"ix":2,"l":2},"a":{"a":0,"k":[44.47,38.214,0],"ix":1,"l":2},"s":{"a":0,"k":[500,500,100],"ix":6,"l":2}},"ao":0,"shapes":[{"ty":"gr","it":[{"ind":0,"ty":"sh","ix":1,"ks":{"a":0,"k":{"i":[[-0.065,-0.498],[0.507,-0.066],[0,0],[0.065,0.498],[-0.507,0.066],[0,0]],"o":[[0.065,0.498],[0,0],[-0.508,0.066],[-0.065,-0.499],[0,0],[0.507,-0.066]],"v":[[8.374,-1.089],[7.581,-0.059],[-7.344,1.882],[-8.374,1.09],[-7.581,0.06],[7.344,-1.882]],"c":true},"ix":2},"nm":"Path 1","mn":"ADBE Vector Shape - Group","hd":false},{"ty":"mm","mm":4,"nm":"Merge Paths 1","mn":"ADBE Vector Filter - Merge","hd":false},{"ty":"fl","c":{"a":0,"k":[1,0.850980451995,0.231372563979,1],"ix":4},"o":{"a":0,"k":100,"ix":5},"r":1,"bm":0,"nm":"Fill 1","mn":"ADBE Vector Graphic - Fill","hd":false},{"ty":"tr","p":{"a":0,"k":[43.985,24.975],"ix":2},"a":{"a":0,"k":[0,0],"ix":1},"s":{"a":0,"k":[100,100],"ix":3},"r":{"a":0,"k":0,"ix":6},"o":{"a":0,"k":100,"ix":7},"sk":{"a":0,"k":0,"ix":4},"sa":{"a":0,"k":0,"ix":5},"nm":"Transform"}],"nm":"Group 2","np":3,"cix":2,"bm":0,"ix":1,"mn":"ADBE Vector Group","hd":false},{"ty":"gr","it":[{"ind":0,"ty":"sh","ix":1,"ks":{"a":0,"k":{"i":[[-0.066,-0.505],[0.513,-0.067],[0,0],[0.067,0.513],[-0.513,0.067],[0,0]],"o":[[0.067,0.513],[0,0],[-0.514,0.067],[-0.066,-0.506],[0,0],[0.514,-0.067]],"v":[[7.49,-0.975],[6.686,0.071],[-6.446,1.779],[-7.491,0.975],[-6.687,-0.07],[6.445,-1.779]],"c":true},"ix":2},"nm":"Path 1","mn":"ADBE Vector Shape - Group","hd":false},{"ty":"mm","mm":4,"nm":"Merge Paths 1","mn":"ADBE Vector Filter - Merge","hd":false},{"ty":"fl","c":{"a":0,"k":[0.352941176471,0.372549019608,0.388235324037,1],"ix":4},"o":{"a":0,"k":100,"ix":5},"r":1,"bm":0,"nm":"Fill 1","mn":"ADBE Vector Graphic - Fill","hd":false},{"ty":"tr","p":{"a":0,"k":[47.444,51.556],"ix":2},"a":{"a":0,"k":[0,0],"ix":1},"s":{"a":0,"k":[100,100],"ix":3},"r":{"a":0,"k":0,"ix":6},"o":{"a":0,"k":100,"ix":7},"sk":{"a":0,"k":0,"ix":4},"sa":{"a":0,"k":0,"ix":5},"nm":"Transform"}],"nm":"Group 3","np":3,"cix":2,"bm":0,"ix":2,"mn":"ADBE Vector Group","hd":false},{"ty":"gr","it":[{"ind":0,"ty":"sh","ix":1,"ks":{"a":0,"k":{"i":[[0.055,0.56],[0,0],[-0.108,-0.521]],"o":[[0,0],[0.091,0.556],[0,0]],"v":[[7.456,-1.781],[-7.51,0.166],[-7.212,1.781]],"c":true},"ix":2},"nm":"Path 1","mn":"ADBE Vector Shape - Group","hd":false},{"ty":"mm","mm":4,"nm":"Merge Paths 1","mn":"ADBE Vector Filter - Merge","hd":false},{"ty":"fl","c":{"a":0,"k":[0.956862804936,0.772549079446,0.203921583587,1],"ix":4},"o":{"a":0,"k":100,"ix":5},"r":1,"bm":0,"nm":"Fill 1","mn":"ADBE Vector Graphic - Fill","hd":false},{"ty":"tr","p":{"a":0,"k":[44.115,26.57],"ix":2},"a":{"a":0,"k":[0,0],"ix":1},"s":{"a":0,"k":[100,100],"ix":3},"r":{"a":0,"k":0,"ix":6},"o":{"a":0,"k":100,"ix":7},"sk":{"a":0,"k":0,"ix":4},"sa":{"a":0,"k":0,"ix":5},"nm":"Transform"}],"nm":"Group 4","np":3,"cix":2,"bm":0,"ix":3,"mn":"ADBE Vector Group","hd":false},{"ty":"gr","it":[{"ind":0,"ty":"sh","ix":1,"ks":{"a":0,"k":{"i":[[0,0],[-3.973,0.517],[0.882,8.947],[0,0]],"o":[[1.436,8.874],[3.973,-0.517],[0,0],[0,0]],"v":[[-7.924,-5.633],[1.337,7.064],[7.042,-7.581],[-7.924,-5.634]],"c":true},"ix":2},"nm":"Path 1","mn":"ADBE Vector Shape - Group","hd":false},{"ty":"mm","mm":4,"nm":"Merge Paths 1","mn":"ADBE Vector Filter - Merge","hd":false},{"ty":"fl","c":{"a":0,"k":[1,0.850980451995,0.231372563979,1],"ix":4},"o":{"a":0,"k":100,"ix":5},"r":1,"bm":0,"nm":"Fill 1","mn":"ADBE Vector Graphic - Fill","hd":false},{"ty":"tr","p":{"a":0,"k":[44.528,32.369],"ix":2},"a":{"a":0,"k":[0,0],"ix":1},"s":{"a":0,"k":[100,100],"ix":3},"r":{"a":0,"k":0,"ix":6},"o":{"a":0,"k":100,"ix":7},"sk":{"a":0,"k":0,"ix":4},"sa":{"a":0,"k":0,"ix":5},"nm":"Transform"}],"nm":"Group 5","np":3,"cix":2,"bm":0,"ix":4,"mn":"ADBE Vector Group","hd":false},{"ty":"gr","it":[{"ind":0,"ty":"sh","ix":1,"ks":{"a":0,"k":{"i":[[0,0],[0,0],[0.26,-0.034],[0,0],[-0.033,-0.26],[0,0],[0,0]],"o":[[0,0],[-0.034,-0.26],[0,0],[-0.261,0.034],[0,0],[0,0],[0,0]],"v":[[6.768,2.617],[5.93,-3.824],[5.402,-4.23],[-6.328,-2.704],[-6.735,-2.176],[-5.897,4.264],[6.768,2.616]],"c":true},"ix":2},"nm":"Path 1","mn":"ADBE Vector Shape - Group","hd":false},{"ty":"mm","mm":4,"nm":"Merge Paths 1","mn":"ADBE Vector Filter - Merge","hd":false},{"ty":"fl","c":{"a":0,"k":[0.243137269862,0.262745098039,0.278431372549,1],"ix":4},"o":{"a":0,"k":100,"ix":5},"r":1,"bm":0,"nm":"Fill 1","mn":"ADBE Vector Graphic - Fill","hd":false},{"ty":"tr","p":{"a":0,"k":[46.964,47.781],"ix":2},"a":{"a":0,"k":[0,0],"ix":1},"s":{"a":0,"k":[100,100],"ix":3},"r":{"a":0,"k":0,"ix":6},"o":{"a":0,"k":100,"ix":7},"sk":{"a":0,"k":0,"ix":4},"sa":{"a":0,"k":0,"ix":5},"nm":"Transform"}],"nm":"Group 6","np":3,"cix":2,"bm":0,"ix":5,"mn":"ADBE Vector Group","hd":false},{"ty":"gr","it":[{"ind":0,"ty":"sh","ix":1,"ks":{"a":0,"k":{"i":[[-0.845,-1.628],[-1.748,-0.892],[-0.961,-0.202],[-2.118,-0.144],[-0.01,0.272],[0.266,0.028],[2.199,0.355],[1.416,0.892],[0.567,1.183],[-0.809,0.814],[-0.503,-0.941],[-0.073,-0.298],[-0.424,0.073],[0.073,0.424],[0.001,0.009],[0.295,0.475],[1.384,-1.516]],"o":[[0.877,1.701],[1.736,0.958],[1.971,0.283],[0.274,0.019],[0.02,-0.265],[-2.391,-0.22],[-0.932,-0.227],[-1.825,-0.968],[-0.516,-1.021],[0.769,-0.818],[0.185,0.298],[0.073,0.424],[0.433,-0.074],[0,0],[-0.094,-0.468],[-1.146,-1.806],[-1.243,1.359]],"v":[[-6.048,0.146],[-1.812,4.1],[2.956,5.63],[6.689,6.01],[7.208,5.555],[6.771,5.035],[3.154,4.583],[-1.255,3.044],[-4.872,-0.467],[-4.938,-3.538],[-2.268,-3.227],[-2.029,-2.499],[-1.133,-1.857],[-0.492,-2.762],[-0.495,-2.781],[-0.947,-4.04],[-5.986,-4.514]],"c":true},"ix":2},"nm":"Path 1","mn":"ADBE Vector Shape - Group","hd":false},{"ty":"mm","mm":4,"nm":"Merge Paths 1","mn":"ADBE Vector Filter - Merge","hd":false},{"ty":"fl","c":{"a":0,"k":[0.956862804936,0.772549079446,0.203921583587,1],"ix":4},"o":{"a":0,"k":100,"ix":5},"r":1,"bm":0,"nm":"Fill 1","mn":"ADBE Vector Graphic - Fill","hd":false},{"ty":"tr","p":{"a":0,"k":[37.94,32.372],"ix":2},"a":{"a":0,"k":[0,0],"ix":1},"s":{"a":0,"k":[100,100],"ix":3},"r":{"a":0,"k":0,"ix":6},"o":{"a":0,"k":100,"ix":7},"sk":{"a":0,"k":0,"ix":4},"sa":{"a":0,"k":0,"ix":5},"nm":"Transform"}],"nm":"Group 7","np":3,"cix":2,"bm":0,"ix":6,"mn":"ADBE Vector Group","hd":false},{"ty":"gr","it":[{"ind":0,"ty":"sh","ix":1,"ks":{"a":0,"k":{"i":[[-0.621,0.081],[0.081,0.62],[0.62,-0.081],[-0.081,-0.621]],"o":[[0.621,-0.081],[-0.081,-0.621],[-0.621,0.08],[0.08,0.621]],"v":[[0.146,1.124],[1.124,-0.146],[-0.146,-1.124],[-1.124,0.146]],"c":true},"ix":2},"nm":"Path 1","mn":"ADBE Vector Shape - Group","hd":false},{"ty":"mm","mm":4,"nm":"Merge Paths 1","mn":"ADBE Vector Filter - Merge","hd":false},{"ty":"fl","c":{"a":0,"k":[0.956862804936,0.772549079446,0.203921583587,1],"ix":4},"o":{"a":0,"k":100,"ix":5},"r":1,"bm":0,"nm":"Fill 1","mn":"ADBE Vector Graphic - Fill","hd":false},{"ty":"tr","p":{"a":0,"k":[36.252,29.705],"ix":2},"a":{"a":0,"k":[0,0],"ix":1},"s":{"a":0,"k":[100,100],"ix":3},"r":{"a":0,"k":0,"ix":6},"o":{"a":0,"k":100,"ix":7},"sk":{"a":0,"k":0,"ix":4},"sa":{"a":0,"k":0,"ix":5},"nm":"Transform"}],"nm":"Group 8","np":3,"cix":2,"bm":0,"ix":7,"mn":"ADBE Vector Group","hd":false},{"ty":"gr","it":[{"ind":0,"ty":"sh","ix":1,"ks":{"a":0,"k":{"i":[[0.4,-1.79],[1.461,-1.31],[0.878,-0.441],[2.011,-0.682],[0.079,0.261],[-0.249,0.096],[-2.034,0.905],[-1.141,1.224],[-0.245,1.289],[0.991,0.58],[0.246,-1.038],[-0.005,-0.307],[0.429,-0.038],[0.038,0.429],[0.001,0.009],[-0.164,0.535],[-1.726,-1.112]],"o":[[-0.412,1.869],[-1.433,1.37],[-1.832,0.778],[-0.259,0.088],[-0.087,-0.251],[2.255,-0.824],[0.844,-0.459],[1.516,-1.403],[0.238,-1.119],[-0.952,-0.594],[-0.102,0.335],[0.038,0.429],[-0.437,0.039],[0,0],[-0.029,-0.477],[0.645,-2.039],[1.549,0.996]],"v":[[5.559,-1.708],[2.477,3.199],[-1.742,5.896],[-5.254,7.221],[-5.872,6.913],[-5.582,6.297],[-2.201,4.937],[1.667,2.32],[4.266,-2.001],[3.543,-4.986],[1.043,-4.001],[0.998,-3.238],[0.296,-2.387],[-0.555,-3.098],[-0.557,-3.117],[-0.442,-4.45],[4.307,-6.197]],"c":true},"ix":2},"nm":"Path 1","mn":"ADBE Vector Shape - Group","hd":false},{"ty":"mm","mm":4,"nm":"Merge Paths 1","mn":"ADBE Vector Filter - Merge","hd":false},{"ty":"fl","c":{"a":0,"k":[0.956862804936,0.772549079446,0.203921583587,1],"ix":4},"o":{"a":0,"k":100,"ix":5},"r":1,"bm":0,"nm":"Fill 1","mn":"ADBE Vector Graphic - Fill","hd":false},{"ty":"tr","p":{"a":0,"k":[52.045,30.881],"ix":2},"a":{"a":0,"k":[0,0],"ix":1},"s":{"a":0,"k":[100,100],"ix":3},"r":{"a":0,"k":0,"ix":6},"o":{"a":0,"k":100,"ix":7},"sk":{"a":0,"k":0,"ix":4},"sa":{"a":0,"k":0,"ix":5},"nm":"Transform"}],"nm":"Group 9","np":3,"cix":2,"bm":0,"ix":8,"mn":"ADBE Vector Group","hd":false},{"ty":"gr","it":[{"ind":0,"ty":"sh","ix":1,"ks":{"a":0,"k":{"i":[[-0.621,0.081],[0.081,0.62],[0.62,-0.081],[-0.081,-0.621]],"o":[[0.621,-0.081],[-0.081,-0.621],[-0.621,0.08],[0.08,0.621]],"v":[[0.146,1.124],[1.124,-0.146],[-0.146,-1.124],[-1.124,0.146]],"c":true},"ix":2},"nm":"Path 1","mn":"ADBE Vector Shape - Group","hd":false},{"ty":"mm","mm":4,"nm":"Merge Paths 1","mn":"ADBE Vector Filter - Merge","hd":false},{"ty":"fl","c":{"a":0,"k":[0.956862804936,0.772549079446,0.203921583587,1],"ix":4},"o":{"a":0,"k":100,"ix":5},"r":1,"bm":0,"nm":"Fill 1","mn":"ADBE Vector Graphic - Fill","hd":false},{"ty":"tr","p":{"a":0,"k":[52.67,27.57],"ix":2},"a":{"a":0,"k":[0,0],"ix":1},"s":{"a":0,"k":[100,100],"ix":3},"r":{"a":0,"k":0,"ix":6},"o":{"a":0,"k":100,"ix":7},"sk":{"a":0,"k":0,"ix":4},"sa":{"a":0,"k":0,"ix":5},"nm":"Transform"}],"nm":"Group 10","np":3,"cix":2,"bm":0,"ix":9,"mn":"ADBE Vector Group","hd":false},{"ty":"gr","it":[{"ind":0,"ty":"sh","ix":1,"ks":{"a":0,"k":{"i":[[-0.413,-0.439],[0,0],[-0.52,0.357],[0.267,2.05],[0,0],[0,0],[0,0],[-1.945,-0.695]],"o":[[0,0],[0.285,-0.533],[1.705,-1.169],[0,0],[0,0],[0,0],[0.267,2.049],[0.597,0.212]],"v":[[5.292,3.787],[-5.292,5.164],[-4.087,3.836],[-1.82,-1.47],[-2.264,-4.896],[-0.208,-5.164],[0.238,-1.733],[3.784,2.816]],"c":true},"ix":2},"nm":"Path 1","mn":"ADBE Vector Shape - Group","hd":false},{"ty":"mm","mm":4,"nm":"Merge Paths 1","mn":"ADBE Vector Filter - Merge","hd":false},{"ty":"fl","c":{"a":0,"k":[0.956862804936,0.772549079446,0.203921583587,1],"ix":4},"o":{"a":0,"k":100,"ix":5},"r":1,"bm":0,"nm":"Fill 1","mn":"ADBE Vector Graphic - Fill","hd":false},{"ty":"tr","p":{"a":0,"k":[46.532,40.073],"ix":2},"a":{"a":0,"k":[0,0],"ix":1},"s":{"a":0,"k":[100,100],"ix":3},"r":{"a":0,"k":0,"ix":6},"o":{"a":0,"k":100,"ix":7},"sk":{"a":0,"k":0,"ix":4},"sa":{"a":0,"k":0,"ix":5},"nm":"Transform"}],"nm":"Group 11","np":3,"cix":2,"bm":0,"ix":10,"mn":"ADBE Vector Group","hd":false}],"ip":0,"op":1694,"st":0,"ct":1,"bm":0},{"ddd":0,"ind":3,"ty":4,"nm":"Layer 3 Outlines","parent":1,"sr":1,"ks":{"o":{"a":0,"k":100,"ix":11},"r":{"a":0,"k":0,"ix":10},"p":{"a":0,"k":[-227.5,210,0],"ix":2,"l":2},"a":{"a":0,"k":[111,38.5,0],"ix":1,"l":2},"s":{"a":0,"k":[500,500,100],"ix":6,"l":2}},"ao":0,"shapes":[{"ty":"gr","it":[{"ind":0,"ty":"sh","ix":1,"ks":{"a":0,"k":{"i":[[0,0],[0,0],[0,0],[-0.52,-0.6]],"o":[[0,0],[0,0],[0.51,-0.6],[0,0]],"v":[[7.02,3.825],[-7.02,3.825],[-0.97,-3.225],[0.98,-3.225]],"c":true},"ix":2},"nm":"Path 1","mn":"ADBE Vector Shape - Group","hd":false},{"ty":"st","c":{"a":0,"k":[1,1,1,1],"ix":3},"o":{"a":0,"k":100,"ix":4},"w":{"a":0,"k":1.429,"ix":5},"lc":1,"lj":1,"ml":4,"bm":0,"nm":"Stroke 1","mn":"ADBE Vector Graphic - Stroke","hd":false},{"ty":"tr","p":{"a":0,"k":[165.57,9.465],"ix":2},"a":{"a":0,"k":[0,0],"ix":1},"s":{"a":0,"k":[100,100],"ix":3},"r":{"a":0,"k":0,"ix":6},"o":{"a":0,"k":100,"ix":7},"sk":{"a":0,"k":0,"ix":4},"sa":{"a":0,"k":0,"ix":5},"nm":"Transform"}],"nm":"Group 1","np":2,"cix":2,"bm":0,"ix":1,"mn":"ADBE Vector Group","hd":false}],"ip":0,"op":1694,"st":0,"ct":1,"bm":0},{"ddd":0,"ind":4,"ty":4,"nm":"Layer 4 Outlines","parent":1,"sr":1,"ks":{"o":{"a":0,"k":100,"ix":11},"r":{"a":0,"k":0,"ix":10},"p":{"a":0,"k":[-227.5,210,0],"ix":2,"l":2},"a":{"a":0,"k":[111,38.5,0],"ix":1,"l":2},"s":{"a":0,"k":[500,500,100],"ix":6,"l":2}},"ao":0,"shapes":[{"ty":"gr","it":[{"ind":0,"ty":"sh","ix":1,"ks":{"a":0,"k":{"i":[[0,0],[0.798,-0.931],[0,0],[0,0]],"o":[[-0.798,-0.931],[0,0],[0,0],[0,0]],"v":[[1.518,-3.648],[-1.519,-3.648],[-8.572,4.579],[8.571,4.579]],"c":true},"ix":2},"nm":"Path 1","mn":"ADBE Vector Shape - Group","hd":false},{"ty":"fl","c":{"a":0,"k":[0.101960791794,0.101960791794,0.101960791794,1],"ix":4},"o":{"a":0,"k":100,"ix":5},"r":1,"bm":0,"nm":"Fill 1","mn":"ADBE Vector Graphic - Fill","hd":false},{"ty":"tr","p":{"a":0,"k":[165.572,9.42],"ix":2},"a":{"a":0,"k":[0,0],"ix":1},"s":{"a":0,"k":[100,100],"ix":3},"r":{"a":0,"k":0,"ix":6},"o":{"a":0,"k":100,"ix":7},"sk":{"a":0,"k":0,"ix":4},"sa":{"a":0,"k":0,"ix":5},"nm":"Transform"}],"nm":"Group 1","np":4,"cix":2,"bm":0,"ix":1,"mn":"ADBE Vector Group","hd":false}],"ip":0,"op":1694,"st":0,"ct":1,"bm":0},{"ddd":0,"ind":5,"ty":4,"nm":"Layer 6 Outlines","parent":1,"sr":1,"ks":{"o":{"a":0,"k":100,"ix":11},"r":{"a":0,"k":0,"ix":10},"p":{"a":0,"k":[-227.5,210,0],"ix":2,"l":2},"a":{"a":0,"k":[111,38.5,0],"ix":1,"l":2},"s":{"a":0,"k":[500,500,100],"ix":6,"l":2}},"ao":0,"shapes":[{"ty":"gr","it":[{"ind":0,"ty":"sh","ix":1,"ks":{"a":0,"k":{"i":[[0.444,0],[0.458,0.279],[0.247,0.503],[0,0.67],[-0.245,0.512],[-0.44,0.286],[-0.591,0],[-0.332,-0.113],[-0.273,-0.255],[-0.162,-0.418],[0,-0.611],[0,0],[0,0],[0,0],[0,0],[0.148,0.29],[0.27,0.167],[0.364,0],[0.293,-0.199],[0.157,-0.316],[0,-0.361],[0,0],[-0.171,-0.344],[-0.307,-0.179],[-0.406,0],[-0.213,0.074],[-0.156,0.15],[-0.086,0.227],[0,0],[0.241,-0.25],[0.355,-0.139]],"o":[[-0.63,0],[-0.454,-0.281],[-0.245,-0.506],[0,-0.67],[0.247,-0.514],[0.443,-0.29],[0.341,0],[0.332,0.114],[0.272,0.253],[0.162,0.418],[0,0],[0,0],[0,0],[0,0],[0,-0.369],[-0.145,-0.29],[-0.267,-0.168],[-0.401,0],[-0.289,0.196],[-0.156,0.315],[0,0],[0,0.495],[0.173,0.34],[0.307,0.176],[0.265,0],[0.216,-0.077],[0.157,-0.154],[0,0],[-0.102,0.329],[-0.242,0.247],[-0.355,0.137]],"v":[[11.281,11.424],[9.648,11.006],[8.596,9.829],[8.23,8.066],[8.596,6.293],[9.628,5.092],[11.178,4.657],[12.189,4.827],[13.096,5.381],[13.749,6.387],[13.992,7.93],[13.992,8.355],[8.945,8.355],[8.945,7.486],[12.969,7.486],[12.747,6.497],[12.124,5.812],[11.178,5.56],[10.139,5.859],[9.469,6.626],[9.236,7.64],[9.236,8.219],[9.492,9.477],[10.212,10.256],[11.281,10.521],[11.997,10.41],[12.555,10.069],[12.917,9.497],[13.889,9.771],[13.374,10.64],[12.479,11.219]],"c":true},"ix":2},"nm":"Path 1","mn":"ADBE Vector Shape - Group","hd":false},{"ind":1,"ty":"sh","ix":2,"ks":{"a":0,"k":{"i":[[0,0],[0,0],[0,0],[0,0],[0,0],[-0.313,0.202],[-0.392,0],[-0.111,-0.003],[-0.057,-0.006],[0,0],[0.122,0.017],[0.134,0],[0.25,-0.134],[0.145,-0.233],[0,-0.296],[0,0]],"o":[[0,0],[0,0],[0,0],[0,0],[0.119,-0.324],[0.312,-0.201],[0.074,0],[0.11,0.003],[0,0],[-0.034,-0.009],[-0.12,-0.02],[-0.318,0],[-0.247,0.13],[-0.142,0.23],[0,0],[0,0]],"v":[[4.271,11.288],[4.271,4.742],[5.243,4.742],[5.243,5.73],[5.311,5.73],[5.958,4.941],[7.016,4.64],[7.292,4.644],[7.544,4.657],[7.544,5.68],[7.31,5.641],[6.93,5.612],[6.077,5.812],[5.49,6.357],[5.277,7.146],[5.277,11.288]],"c":true},"ix":2},"nm":"Path 2","mn":"ADBE Vector Shape - Group","hd":false},{"ind":2,"ty":"sh","ix":3,"ks":{"a":0,"k":{"i":[[0.444,0],[0.458,0.279],[0.247,0.503],[0,0.67],[-0.245,0.512],[-0.44,0.286],[-0.591,0],[-0.332,-0.113],[-0.273,-0.255],[-0.162,-0.418],[0,-0.611],[0,0],[0,0],[0,0],[0,0],[0.148,0.29],[0.27,0.167],[0.364,0],[0.293,-0.199],[0.157,-0.316],[0,-0.361],[0,0],[-0.171,-0.344],[-0.307,-0.179],[-0.406,0],[-0.213,0.074],[-0.156,0.15],[-0.086,0.227],[0,0],[0.241,-0.25],[0.355,-0.139]],"o":[[-0.63,0],[-0.454,-0.281],[-0.245,-0.506],[0,-0.67],[0.247,-0.514],[0.443,-0.29],[0.341,0],[0.332,0.114],[0.272,0.253],[0.162,0.418],[0,0],[0,0],[0,0],[0,0],[0,-0.369],[-0.145,-0.29],[-0.267,-0.168],[-0.401,0],[-0.289,0.196],[-0.156,0.315],[0,0],[0,0.495],[0.173,0.34],[0.307,0.176],[0.265,0],[0.216,-0.077],[0.157,-0.154],[0,0],[-0.102,0.329],[-0.242,0.247],[-0.355,0.137]],"v":[[0.031,11.424],[-1.602,11.006],[-2.654,9.829],[-3.021,8.066],[-2.654,6.293],[-1.622,5.092],[-0.072,4.657],[0.939,4.827],[1.846,5.381],[2.499,6.387],[2.742,7.93],[2.742,8.355],[-2.305,8.355],[-2.305,7.486],[1.719,7.486],[1.497,6.497],[0.874,5.812],[-0.072,5.56],[-1.111,5.859],[-1.781,6.626],[-2.014,7.64],[-2.014,8.219],[-1.758,9.477],[-1.038,10.256],[0.031,10.521],[0.747,10.41],[1.305,10.069],[1.667,9.497],[2.639,9.771],[2.124,10.64],[1.229,11.219]],"c":true},"ix":2},"nm":"Path 3","mn":"ADBE Vector Shape - Group","hd":false},{"ind":3,"ty":"sh","ix":4,"ks":{"a":0,"k":{"i":[[0,-0.381],[0,0],[0,0],[0,0],[0,0],[0,0],[0,0],[-0.306,0.198],[-0.514,0],[-0.335,-0.179],[-0.185,-0.366],[0,-0.562],[0,0],[0,0],[0,0],[0.27,0.284],[0.475,0],[0.261,-0.139],[0.151,-0.266]],"o":[[0,0],[0,0],[0,0],[0,0],[0,0],[0,0],[0.153,-0.338],[0.31,-0.202],[0.446,0],[0.335,0.177],[0.187,0.364],[0,0],[0,0],[0,0],[0,-0.52],[-0.267,-0.287],[-0.329,0],[-0.258,0.139],[-0.147,0.268]],"v":[[-8.798,7.35],[-8.798,11.288],[-9.803,11.288],[-9.803,2.56],[-8.798,2.56],[-8.798,5.765],[-8.712,5.765],[-8.023,4.96],[-6.786,4.657],[-5.615,4.924],[-4.835,5.739],[-4.553,7.128],[-4.553,11.288],[-5.559,11.288],[-5.559,7.197],[-5.964,5.991],[-7.077,5.56],[-7.962,5.769],[-8.577,6.378]],"c":true},"ix":2},"nm":"Path 4","mn":"ADBE Vector Shape - Group","hd":false},{"ind":4,"ty":"sh","ix":5,"ks":{"a":0,"k":{"i":[[0.443,0],[0.457,0.279],[0.248,0.503],[0,0.67],[-0.244,0.512],[-0.441,0.286],[-0.591,0],[-0.333,-0.113],[-0.272,-0.255],[-0.161,-0.418],[0,-0.611],[0,0],[0,0],[0,0],[0,0],[0.148,0.29],[0.27,0.167],[0.363,0],[0.293,-0.199],[0.156,-0.316],[0,-0.361],[0,0],[-0.17,-0.344],[-0.307,-0.179],[-0.406,0],[-0.213,0.074],[-0.156,0.15],[-0.085,0.227],[0,0],[0.242,-0.25],[0.355,-0.139]],"o":[[-0.631,0],[-0.455,-0.281],[-0.244,-0.506],[0,-0.67],[0.248,-0.514],[0.443,-0.29],[0.341,0],[0.332,0.114],[0.273,0.253],[0.162,0.418],[0,0],[0,0],[0,0],[0,0],[0,-0.369],[-0.145,-0.29],[-0.267,-0.168],[-0.401,0],[-0.29,0.196],[-0.156,0.315],[0,0],[0,0.495],[0.174,0.34],[0.306,0.176],[0.264,0],[0.216,-0.077],[0.157,-0.154],[0,0],[-0.102,0.329],[-0.241,0.247],[-0.356,0.137]],"v":[[-17.419,11.424],[-19.051,11.006],[-20.104,9.829],[-20.469,8.066],[-20.104,6.293],[-19.072,5.092],[-17.521,4.657],[-16.51,4.827],[-15.604,5.381],[-14.952,6.387],[-14.708,7.93],[-14.708,8.355],[-19.753,8.355],[-19.753,7.486],[-15.73,7.486],[-15.952,6.497],[-16.574,5.812],[-17.521,5.56],[-18.561,5.859],[-19.23,6.626],[-19.464,7.64],[-19.464,8.219],[-19.208,9.477],[-18.488,10.256],[-17.419,10.521],[-16.702,10.41],[-16.145,10.069],[-15.783,9.497],[-14.811,9.771],[-15.327,10.64],[-16.221,11.219]],"c":true},"ix":2},"nm":"Path 5","mn":"ADBE Vector Shape - Group","hd":false},{"ind":5,"ty":"sh","ix":6,"ks":{"a":0,"k":{"i":[[0,0],[0,0],[0,0],[0,0]],"o":[[0,0],[0,0],[0,0],[0,0]],"v":[[-22.005,11.288],[-23.01,11.288],[-23.01,2.561],[-22.005,2.561]],"c":true},"ix":2},"nm":"Path 6","mn":"ADBE Vector Shape - Group","hd":false},{"ind":6,"ty":"sh","ix":7,"ks":{"a":0,"k":{"i":[[0,0]],"o":[[0,0]],"v":[[-22.005,2.56]],"c":false},"ix":2},"nm":"Path 7","mn":"ADBE Vector Shape - Group","hd":false},{"ind":7,"ty":"sh","ix":8,"ks":{"a":0,"k":{"i":[[0,-0.489],[-0.145,-0.378],[-0.278,-0.213],[-0.403,0],[-0.282,0.222],[-0.142,0.378],[0,0.466],[0.142,0.369],[0.284,0.216],[0.426,0],[0.278,-0.207],[0.142,-0.369]],"o":[[0,0.494],[0.145,0.375],[0.279,0.21],[0.42,0],[0.284,-0.224],[0.145,-0.381],[0,-0.46],[-0.139,-0.373],[-0.281,-0.218],[-0.409,0],[-0.279,0.205],[-0.142,0.367]],"v":[[-29.339,8.015],[-29.122,9.323],[-28.486,10.204],[-27.464,10.521],[-26.411,10.188],[-25.771,9.285],[-25.555,8.015],[-25.768,6.771],[-26.402,5.887],[-27.464,5.56],[-28.495,5.87],[-29.126,6.732]],"c":true},"ix":2},"nm":"Path 8","mn":"ADBE Vector Shape - Group","hd":false},{"ind":8,"ty":"sh","ix":9,"ks":{"a":0,"k":{"i":[[0,0],[0,0],[0,0],[0,0],[0,0],[-0.131,0.176],[-0.247,0.139],[-0.426,0],[-0.421,-0.275],[-0.236,-0.505],[0,-0.688],[0.236,-0.509],[0.418,-0.279],[0.546,0],[0.253,0.139],[0.136,0.179],[0.074,0.119],[0,0],[0,0]],"o":[[0,0],[0,0],[0,0],[0,0],[0.074,-0.114],[0.134,-0.179],[0.25,-0.142],[0.551,0],[0.42,0.276],[0.236,0.506],[0,0.693],[-0.236,0.505],[-0.418,0.275],[-0.42,0],[-0.252,-0.142],[-0.137,-0.182],[0,0],[0,0],[0,0]],"v":[[-30.327,11.288],[-30.327,2.56],[-29.322,2.56],[-29.322,5.782],[-29.236,5.782],[-28.93,5.346],[-28.359,4.87],[-27.344,4.657],[-25.887,5.07],[-24.902,6.242],[-24.548,8.032],[-24.902,9.835],[-25.882,11.01],[-27.327,11.424],[-28.337,11.215],[-28.921,10.734],[-29.236,10.282],[-29.355,10.282],[-29.355,11.288]],"c":true},"ix":2},"nm":"Path 9","mn":"ADBE Vector Shape - Group","hd":false},{"ind":9,"ty":"sh","ix":10,"ks":{"a":0,"k":{"i":[[-0.401,0],[-0.272,0.157],[-0.14,0.247],[0,0.273],[0,0],[0.145,-0.042],[0.188,-0.031],[0.176,-0.023],[0.108,-0.014],[0.227,-0.077],[0.139,-0.151],[0,-0.256],[-0.259,-0.179]],"o":[[0.398,0],[0.276,-0.156],[0.142,-0.247],[0,0],[-0.043,0.051],[-0.141,0.04],[-0.185,0.028],[-0.173,0.02],[-0.261,0.034],[-0.224,0.074],[-0.137,0.147],[0,0.349],[0.261,0.176]],"v":[[-35.145,10.538],[-34.141,10.303],[-33.518,9.698],[-33.305,8.918],[-33.305,7.997],[-33.587,8.138],[-34.081,8.245],[-34.622,8.322],[-35.044,8.372],[-35.777,8.538],[-36.322,8.876],[-36.527,9.48],[-36.139,10.273]],"c":true},"ix":2},"nm":"Path 10","mn":"ADBE Vector Shape - Group","hd":false},{"ind":10,"ty":"sh","ix":11,"ks":{"a":0,"k":{"i":[[0.381,0],[0.338,0.156],[0.199,0.298],[0,0.426],[-0.148,0.233],[-0.247,0.133],[-0.299,0.066],[-0.304,0.04],[-0.248,0.026],[-0.114,0.065],[0,0.162],[0,0],[0.23,0.233],[0.463,0],[0.272,-0.211],[0.111,-0.239],[0,0],[-0.284,0.222],[-0.338,0.088],[-0.33,0],[-0.272,-0.052],[-0.255,-0.153],[-0.171,-0.31],[0,-0.52],[0,0],[0,0],[0,0],[0,0],[0.159,-0.162],[0.264,-0.114]],"o":[[-0.414,0],[-0.338,-0.159],[-0.199,-0.302],[0,-0.375],[0.148,-0.236],[0.248,-0.134],[0.301,-0.068],[0.398,-0.051],[0.25,-0.028],[0.116,-0.066],[0,0],[0,-0.421],[-0.228,-0.233],[-0.48,0],[-0.273,0.21],[0,0],[0.17,-0.398],[0.287,-0.224],[0.341,-0.091],[0.21,0],[0.276,0.048],[0.259,0.154],[0.17,0.309],[0,0],[0,0],[0,0],[0,0],[-0.069,0.142],[-0.159,0.162],[-0.264,0.113]],"v":[[-35.299,11.441],[-36.428,11.207],[-37.234,10.521],[-37.533,9.43],[-37.311,8.518],[-36.719,7.964],[-35.9,7.665],[-34.992,7.503],[-34.025,7.388],[-33.479,7.247],[-33.305,6.907],[-33.305,6.872],[-33.65,5.893],[-34.686,5.543],[-35.814,5.859],[-36.391,6.532],[-37.344,6.191],[-36.663,5.262],[-35.725,4.793],[-34.719,4.657],[-33.995,4.734],[-33.199,5.036],[-32.555,5.73],[-32.299,6.975],[-32.299,11.288],[-33.305,11.288],[-33.305,10.4],[-33.355,10.4],[-33.697,10.857],[-34.331,11.271]],"c":true},"ix":2},"nm":"Path 11","mn":"ADBE Vector Shape - Group","hd":false},{"ind":11,"ty":"sh","ix":12,"ks":{"a":0,"k":{"i":[[0,0],[0,0],[0,0],[0,0]],"o":[[0,0],[0,0],[0,0],[0,0]],"v":[[-39.068,11.288],[-40.074,11.288],[-40.074,2.561],[-39.068,2.561]],"c":true},"ix":2},"nm":"Path 12","mn":"ADBE Vector Shape - Group","hd":false},{"ind":12,"ty":"sh","ix":13,"ks":{"a":0,"k":{"i":[[0,0]],"o":[[0,0]],"v":[[-39.068,2.56]],"c":false},"ix":2},"nm":"Path 13","mn":"ADBE Vector Shape - Group","hd":false},{"ind":13,"ty":"sh","ix":14,"ks":{"a":0,"k":{"i":[[0.196,0],[0.142,0.134],[0,0.188],[-0.139,0.133],[-0.196,0],[-0.139,-0.134],[0,-0.187],[0.142,-0.134]],"o":[[-0.196,0],[-0.139,-0.134],[0,-0.187],[0.142,-0.134],[0.196,0],[0.142,0.133],[0,0.188],[-0.139,0.134]],"v":[[-42.41,3.65],[-42.917,3.451],[-43.126,2.969],[-42.917,2.488],[-42.41,2.288],[-41.906,2.488],[-41.693,2.969],[-41.906,3.451]],"c":true},"ix":2},"nm":"Path 14","mn":"ADBE Vector Shape - Group","hd":false},{"ind":14,"ty":"sh","ix":15,"ks":{"a":0,"k":{"i":[[0,0],[0,0],[0,0],[0,0]],"o":[[0,0],[0,0],[0,0],[0,0]],"v":[[-42.921,4.742],[-41.915,4.742],[-41.915,11.288],[-42.921,11.288]],"c":true},"ix":2},"nm":"Path 15","mn":"ADBE Vector Shape - Group","hd":false},{"ind":15,"ty":"sh","ix":16,"ks":{"a":0,"k":{"i":[[0,0]],"o":[[0,0]],"v":[[-42.921,11.288]],"c":false},"ix":2},"nm":"Path 16","mn":"ADBE Vector Shape - Group","hd":false},{"ind":16,"ty":"sh","ix":17,"ks":{"a":0,"k":{"i":[[-0.401,0],[-0.272,0.157],[-0.14,0.247],[0,0.273],[0,0],[0.145,-0.042],[0.188,-0.031],[0.176,-0.023],[0.108,-0.014],[0.227,-0.077],[0.139,-0.151],[0,-0.256],[-0.259,-0.179]],"o":[[0.397,0],[0.276,-0.156],[0.142,-0.247],[0,0],[-0.043,0.051],[-0.142,0.04],[-0.185,0.028],[-0.173,0.02],[-0.261,0.034],[-0.224,0.074],[-0.137,0.147],[0,0.349],[0.261,0.176]],"v":[[-47.602,10.538],[-46.598,10.303],[-45.975,9.698],[-45.762,8.918],[-45.762,7.997],[-46.044,8.138],[-46.538,8.245],[-47.079,8.322],[-47.501,8.372],[-48.234,8.538],[-48.779,8.876],[-48.984,9.48],[-48.596,10.273]],"c":true},"ix":2},"nm":"Path 17","mn":"ADBE Vector Shape - Group","hd":false},{"ind":17,"ty":"sh","ix":18,"ks":{"a":0,"k":{"i":[[0.381,0],[0.338,0.156],[0.199,0.298],[0,0.426],[-0.148,0.233],[-0.247,0.133],[-0.299,0.066],[-0.304,0.04],[-0.248,0.026],[-0.114,0.065],[0,0.162],[0,0],[0.23,0.233],[0.463,0],[0.273,-0.211],[0.111,-0.239],[0,0],[-0.284,0.222],[-0.338,0.088],[-0.33,0],[-0.272,-0.052],[-0.255,-0.153],[-0.171,-0.31],[0,-0.52],[0,0],[0,0],[0,0],[0,0],[0.159,-0.162],[0.264,-0.114]],"o":[[-0.414,0],[-0.338,-0.159],[-0.199,-0.302],[0,-0.375],[0.148,-0.236],[0.248,-0.134],[0.301,-0.068],[0.398,-0.051],[0.25,-0.028],[0.116,-0.066],[0,0],[0,-0.421],[-0.228,-0.233],[-0.48,0],[-0.273,0.21],[0,0],[0.17,-0.398],[0.287,-0.224],[0.341,-0.091],[0.21,0],[0.276,0.048],[0.259,0.154],[0.17,0.309],[0,0],[0,0],[0,0],[0,0],[-0.069,0.142],[-0.159,0.162],[-0.264,0.113]],"v":[[-47.757,11.441],[-48.885,11.207],[-49.691,10.521],[-49.99,9.43],[-49.768,8.518],[-49.176,7.964],[-48.357,7.665],[-47.449,7.503],[-46.482,7.388],[-45.936,7.247],[-45.762,6.907],[-45.762,6.872],[-46.107,5.893],[-47.143,5.543],[-48.271,5.859],[-48.848,6.532],[-49.801,6.191],[-49.12,5.262],[-48.182,4.793],[-47.176,4.657],[-46.452,4.734],[-45.656,5.036],[-45.012,5.73],[-44.757,6.975],[-44.757,11.288],[-45.762,11.288],[-45.762,10.4],[-45.812,10.4],[-46.154,10.857],[-46.788,11.271]],"c":true},"ix":2},"nm":"Path 18","mn":"ADBE Vector Shape - Group","hd":false},{"ind":18,"ty":"sh","ix":19,"ks":{"a":0,"k":{"i":[[0,0],[0,0],[0,0],[0,0],[0,0],[0,0],[0,0],[0,0]],"o":[[0,0],[0,0],[0,0],[0,0],[0,0],[0,0],[0,0],[0,0]],"v":[[-50.811,4.742],[-53.23,11.288],[-54.253,11.288],[-56.674,4.742],[-55.583,4.742],[-53.777,9.958],[-53.708,9.958],[-51.902,4.742]],"c":true},"ix":2},"nm":"Path 19","mn":"ADBE Vector Shape - Group","hd":false},{"ind":19,"ty":"sh","ix":20,"ks":{"a":0,"k":{"i":[[-0.401,0],[-0.273,0.157],[-0.139,0.247],[0,0.273],[0,0],[0.144,-0.042],[0.188,-0.031],[0.176,-0.023],[0.108,-0.014],[0.228,-0.077],[0.139,-0.151],[0,-0.256],[-0.258,-0.179]],"o":[[0.398,0],[0.275,-0.156],[0.142,-0.247],[0,0],[-0.043,0.051],[-0.142,0.04],[-0.184,0.028],[-0.173,0.02],[-0.261,0.034],[-0.224,0.074],[-0.137,0.147],[0,0.349],[0.262,0.176]],"v":[[-60.611,10.538],[-59.605,10.303],[-58.982,9.698],[-58.77,8.918],[-58.77,7.997],[-59.051,8.138],[-59.546,8.245],[-60.087,8.322],[-60.508,8.372],[-61.242,8.538],[-61.786,8.876],[-61.992,9.48],[-61.604,10.273]],"c":true},"ix":2},"nm":"Path 20","mn":"ADBE Vector Shape - Group","hd":false},{"ind":20,"ty":"sh","ix":21,"ks":{"a":0,"k":{"i":[[0.38,0],[0.338,0.156],[0.199,0.298],[0,0.426],[-0.148,0.233],[-0.248,0.133],[-0.299,0.066],[-0.304,0.04],[-0.247,0.026],[-0.113,0.065],[0,0.162],[0,0],[0.23,0.233],[0.463,0],[0.273,-0.211],[0.11,-0.239],[0,0],[-0.284,0.222],[-0.338,0.088],[-0.329,0],[-0.273,-0.052],[-0.255,-0.153],[-0.171,-0.31],[0,-0.52],[0,0],[0,0],[0,0],[0,0],[0.159,-0.162],[0.264,-0.114]],"o":[[-0.415,0],[-0.338,-0.159],[-0.199,-0.302],[0,-0.375],[0.148,-0.236],[0.247,-0.134],[0.301,-0.068],[0.398,-0.051],[0.25,-0.028],[0.117,-0.066],[0,0],[0,-0.421],[-0.227,-0.233],[-0.48,0],[-0.273,0.21],[0,0],[0.171,-0.398],[0.287,-0.224],[0.341,-0.091],[0.21,0],[0.275,0.048],[0.259,0.154],[0.17,0.309],[0,0],[0,0],[0,0],[0,0],[-0.068,0.142],[-0.159,0.162],[-0.264,0.113]],"v":[[-60.764,11.441],[-61.894,11.207],[-62.699,10.521],[-62.997,9.43],[-62.775,8.518],[-62.182,7.964],[-61.365,7.665],[-60.458,7.503],[-59.49,7.388],[-58.945,7.247],[-58.77,6.907],[-58.77,6.872],[-59.115,5.893],[-60.15,5.543],[-61.279,5.859],[-61.855,6.532],[-62.809,6.191],[-62.128,5.262],[-61.191,4.793],[-60.184,4.657],[-59.46,4.734],[-58.663,5.036],[-58.02,5.73],[-57.764,6.975],[-57.764,11.288],[-58.77,11.288],[-58.77,10.4],[-58.82,10.4],[-59.161,10.857],[-59.797,11.271]],"c":true},"ix":2},"nm":"Path 21","mn":"ADBE Vector Shape - Group","hd":false},{"ind":21,"ty":"sh","ix":22,"ks":{"a":0,"k":{"i":[[0.443,0],[0.457,0.279],[0.247,0.503],[0,0.671],[-0.244,0.512],[-0.44,0.286],[-0.591,0],[-0.333,-0.113],[-0.273,-0.255],[-0.162,-0.418],[0,-0.611],[0,0],[0,0],[0,0],[0,0],[0.147,0.29],[0.269,0.167],[0.363,0],[0.292,-0.199],[0.156,-0.316],[0,-0.361],[0,0],[-0.17,-0.344],[-0.307,-0.179],[-0.406,0],[-0.213,0.074],[-0.156,0.15],[-0.085,0.227],[0,0],[0.242,-0.25],[0.355,-0.139]],"o":[[-0.631,0],[-0.455,-0.281],[-0.244,-0.506],[0,-0.67],[0.247,-0.514],[0.444,-0.29],[0.34,0],[0.332,0.114],[0.273,0.253],[0.162,0.418],[0,0],[0,0],[0,0],[0,0],[0,-0.37],[-0.145,-0.29],[-0.267,-0.168],[-0.401,0],[-0.29,0.196],[-0.156,0.315],[0,0],[0,0.495],[0.173,0.34],[0.307,0.176],[0.264,0],[0.216,-0.077],[0.156,-0.154],[0,0],[-0.102,0.329],[-0.241,0.247],[-0.355,0.137]],"v":[[60.594,-2.577],[58.962,-2.995],[57.909,-4.171],[57.543,-5.934],[57.909,-7.708],[58.939,-8.909],[60.492,-9.344],[61.501,-9.174],[62.409,-8.62],[63.061,-7.613],[63.303,-6.07],[63.303,-5.645],[58.258,-5.645],[58.258,-6.514],[62.281,-6.514],[62.06,-7.503],[61.438,-8.189],[60.492,-8.441],[59.452,-8.141],[58.783,-7.374],[58.548,-6.361],[58.548,-5.781],[58.803,-4.523],[59.523,-3.745],[60.594,-3.48],[61.31,-3.59],[61.868,-3.932],[62.23,-4.503],[63.202,-4.23],[62.686,-3.361],[61.79,-2.781]],"c":true},"ix":2},"nm":"Path 22","mn":"ADBE Vector Shape - Group","hd":false},{"ind":22,"ty":"sh","ix":23,"ks":{"a":0,"k":{"i":[[0,0],[0,0],[0,0],[0,0],[0,0],[-0.312,0.202],[-0.392,0],[-0.111,-0.003],[-0.057,-0.006],[0,0],[0.122,0.017],[0.134,0],[0.25,-0.134],[0.145,-0.233],[0,-0.296],[0,0]],"o":[[0,0],[0,0],[0,0],[0,0],[0.119,-0.324],[0.313,-0.201],[0.074,0],[0.111,0.003],[0,0],[-0.034,-0.009],[-0.119,-0.02],[-0.318,0],[-0.247,0.13],[-0.142,0.23],[0,0],[0,0]],"v":[[53.583,-2.712],[53.583,-9.258],[54.555,-9.258],[54.555,-8.27],[54.624,-8.27],[55.271,-9.059],[56.327,-9.361],[56.605,-9.357],[56.857,-9.344],[56.857,-8.32],[56.622,-8.359],[56.243,-8.389],[55.391,-8.189],[54.803,-7.643],[54.59,-6.855],[54.59,-2.712]],"c":true},"ix":2},"nm":"Path 23","mn":"ADBE Vector Shape - Group","hd":false},{"ind":23,"ty":"sh","ix":24,"ks":{"a":0,"k":{"i":[[-0.401,0],[-0.272,0.157],[-0.14,0.247],[0,0.273],[0,0],[0.145,-0.042],[0.188,-0.031],[0.176,-0.023],[0.108,-0.014],[0.227,-0.077],[0.139,-0.151],[0,-0.256],[-0.259,-0.179]],"o":[[0.397,0],[0.276,-0.156],[0.142,-0.247],[0,0],[-0.043,0.051],[-0.142,0.04],[-0.185,0.028],[-0.173,0.02],[-0.261,0.034],[-0.224,0.074],[-0.137,0.147],[0,0.349],[0.261,0.176]],"v":[[48.902,-3.462],[49.906,-3.697],[50.53,-4.303],[50.743,-5.083],[50.743,-6.003],[50.461,-5.863],[49.967,-5.756],[49.426,-5.678],[49.004,-5.628],[48.271,-5.462],[47.725,-5.124],[47.521,-4.52],[47.909,-3.727]],"c":true},"ix":2},"nm":"Path 24","mn":"ADBE Vector Shape - Group","hd":false},{"ind":24,"ty":"sh","ix":25,"ks":{"a":0,"k":{"i":[[0.381,0],[0.338,0.156],[0.199,0.298],[0,0.426],[-0.148,0.233],[-0.247,0.133],[-0.298,0.066],[-0.304,0.04],[-0.247,0.026],[-0.114,0.065],[0,0.162],[0,0],[0.231,0.233],[0.463,0],[0.272,-0.211],[0.111,-0.239],[0,0],[-0.284,0.222],[-0.338,0.088],[-0.33,0],[-0.272,-0.052],[-0.256,-0.153],[-0.171,-0.31],[0,-0.52],[0,0],[0,0],[0,0],[0,0],[0.159,-0.162],[0.264,-0.114]],"o":[[-0.414,0],[-0.338,-0.159],[-0.199,-0.302],[0,-0.375],[0.148,-0.236],[0.247,-0.134],[0.302,-0.068],[0.398,-0.051],[0.25,-0.028],[0.116,-0.066],[0,0],[0,-0.421],[-0.227,-0.233],[-0.48,0],[-0.273,0.21],[0,0],[0.17,-0.398],[0.287,-0.224],[0.341,-0.091],[0.21,0],[0.276,0.048],[0.259,0.154],[0.17,0.309],[0,0],[0,0],[0,0],[0,0],[-0.068,0.142],[-0.16,0.162],[-0.265,0.113]],"v":[[48.747,-2.559],[47.618,-2.794],[46.814,-3.48],[46.514,-4.57],[46.737,-5.482],[47.329,-6.036],[48.146,-6.335],[49.055,-6.497],[50.021,-6.613],[50.568,-6.753],[50.743,-7.094],[50.743,-7.128],[50.396,-8.107],[49.362,-8.458],[48.232,-8.141],[47.656,-7.469],[46.702,-7.809],[47.385,-8.738],[48.322,-9.208],[49.327,-9.344],[50.051,-9.266],[50.849,-8.965],[51.493,-8.27],[51.747,-7.025],[51.747,-2.712],[50.743,-2.712],[50.743,-3.6],[50.691,-3.6],[50.35,-3.143],[49.715,-2.73]],"c":true},"ix":2},"nm":"Path 25","mn":"ADBE Vector Shape - Group","hd":false},{"ind":25,"ty":"sh","ix":26,"ks":{"a":0,"k":{"i":[[-0.156,-0.466],[0,0],[0.111,0.142],[0.187,0.094],[0.292,0],[0.267,-0.184],[0,-0.281],[-0.182,-0.145],[-0.386,-0.096],[0,0],[-0.287,-0.293],[0,-0.458],[0.216,-0.295],[0.383,-0.17],[0.508,0],[0.437,0.29],[0.116,0.557],[0,0],[-0.253,-0.176],[-0.411,0],[-0.276,0.199],[0,0.281],[0.159,0.153],[0.33,0.077],[0,0],[0.281,0.299],[0,0.452],[-0.207,0.284],[-0.361,0.162],[-0.46,0],[-0.369,-0.284]],"o":[[0,0],[-0.057,-0.151],[-0.108,-0.145],[-0.188,-0.094],[-0.401,0],[-0.264,0.182],[0,0.25],[0.182,0.145],[0,0],[0.585,0.142],[0.287,0.29],[0,0.375],[-0.213,0.296],[-0.384,0.171],[-0.668,0],[-0.438,-0.29],[0,0],[0.091,0.352],[0.256,0.176],[0.469,0],[0.278,-0.201],[0,-0.227],[-0.159,-0.156],[0,0],[-0.599,-0.142],[-0.278,-0.301],[0,-0.369],[0.211,-0.284],[0.364,-0.162],[0.648,0],[0.373,0.284]],"v":[[41.814,-7.792],[40.911,-7.536],[40.659,-7.975],[40.215,-8.333],[39.495,-8.475],[38.493,-8.197],[38.098,-7.503],[38.37,-6.911],[39.223,-6.549],[40.195,-6.309],[41.503,-5.658],[41.932,-4.536],[41.609,-3.531],[40.715,-2.833],[39.376,-2.577],[37.719,-3.011],[36.887,-4.281],[37.842,-4.52],[38.357,-3.727],[39.359,-3.462],[40.475,-3.762],[40.894,-4.486],[40.655,-5.057],[39.922,-5.406],[38.831,-5.661],[37.51,-6.322],[37.092,-7.452],[37.402,-8.432],[38.26,-9.1],[39.495,-9.344],[41.021,-8.917]],"c":true},"ix":2},"nm":"Path 26","mn":"ADBE Vector Shape - Group","hd":false},{"ind":26,"ty":"sh","ix":27,"ks":{"a":0,"k":{"i":[[-0.42,0],[-0.278,0.21],[-0.145,0.375],[0,0.494],[0.142,0.367],[0.278,0.205],[0.41,0],[0.284,-0.218],[0.142,-0.373],[0,-0.46],[-0.142,-0.381],[-0.282,-0.224]],"o":[[0.404,0],[0.279,-0.213],[0.145,-0.378],[0,-0.489],[-0.142,-0.369],[-0.279,-0.207],[-0.426,0],[-0.281,0.216],[-0.139,0.369],[0,0.466],[0.145,0.378],[0.284,0.222]],"v":[[32.331,-3.48],[33.355,-3.796],[33.99,-4.678],[34.206,-5.986],[33.993,-7.268],[33.363,-8.13],[32.331,-8.441],[31.267,-8.113],[30.632,-7.23],[30.423,-5.986],[30.635,-4.715],[31.275,-3.812]],"c":true},"ix":2},"nm":"Path 27","mn":"ADBE Vector Shape - Group","hd":false},{"ind":27,"ty":"sh","ix":28,"ks":{"a":0,"k":{"i":[[0.421,0],[0.417,0.275],[0.236,0.505],[0,0.693],[-0.235,0.506],[-0.421,0.276],[-0.551,0],[-0.247,-0.142],[-0.131,-0.179],[-0.074,-0.114],[0,0],[0,0],[0,0],[0,0],[0,0],[0,0],[0,0],[0.136,-0.182],[0.253,-0.142]],"o":[[-0.545,0],[-0.418,-0.279],[-0.235,-0.509],[0,-0.688],[0.236,-0.505],[0.42,-0.275],[0.426,0],[0.25,0.139],[0.134,0.176],[0,0],[0,0],[0,0],[0,0],[0,0],[0,0],[0,0],[-0.074,0.119],[-0.137,0.179],[-0.253,0.139]],"v":[[32.195,-2.577],[30.751,-2.99],[29.771,-4.165],[29.417,-5.969],[29.771,-7.758],[30.756,-8.93],[32.212,-9.344],[33.223,-9.131],[33.794,-8.654],[34.105,-8.219],[34.189,-8.219],[34.189,-11.441],[35.195,-11.441],[35.195,-2.712],[34.225,-2.712],[34.225,-3.719],[34.105,-3.719],[33.79,-3.266],[33.206,-2.785]],"c":true},"ix":2},"nm":"Path 28","mn":"ADBE Vector Shape - Group","hd":false},{"ind":28,"ty":"sh","ix":29,"ks":{"a":0,"k":{"i":[[0,0],[0,0],[0,0],[0,0],[0,0],[-0.312,0.202],[-0.392,0],[-0.111,-0.003],[-0.057,-0.006],[0,0],[0.122,0.017],[0.134,0],[0.25,-0.134],[0.145,-0.233],[0,-0.296],[0,0]],"o":[[0,0],[0,0],[0,0],[0,0],[0.119,-0.324],[0.313,-0.201],[0.074,0],[0.111,0.003],[0,0],[-0.034,-0.009],[-0.119,-0.02],[-0.318,0],[-0.247,0.13],[-0.142,0.23],[0,0],[0,0]],"v":[[25.458,-2.712],[25.458,-9.258],[26.43,-9.258],[26.43,-8.27],[26.499,-8.27],[27.146,-9.059],[28.202,-9.361],[28.48,-9.357],[28.732,-9.344],[28.732,-8.32],[28.497,-8.359],[28.118,-8.389],[27.266,-8.189],[26.678,-7.643],[26.465,-6.855],[26.465,-2.712]],"c":true},"ix":2},"nm":"Path 29","mn":"ADBE Vector Shape - Group","hd":false},{"ind":29,"ty":"sh","ix":30,"ks":{"a":0,"k":{"i":[[-0.401,0],[-0.272,0.157],[-0.14,0.247],[0,0.273],[0,0],[0.145,-0.042],[0.188,-0.031],[0.176,-0.023],[0.108,-0.014],[0.227,-0.077],[0.139,-0.151],[0,-0.256],[-0.259,-0.179]],"o":[[0.397,0],[0.276,-0.156],[0.142,-0.247],[0,0],[-0.043,0.051],[-0.142,0.04],[-0.185,0.028],[-0.173,0.02],[-0.261,0.034],[-0.224,0.074],[-0.137,0.147],[0,0.349],[0.261,0.176]],"v":[[20.777,-3.462],[21.782,-3.697],[22.404,-4.303],[22.618,-5.083],[22.618,-6.003],[22.336,-5.863],[21.842,-5.756],[21.301,-5.678],[20.879,-5.628],[20.146,-5.462],[19.6,-5.124],[19.396,-4.52],[19.784,-3.727]],"c":true},"ix":2},"nm":"Path 30","mn":"ADBE Vector Shape - Group","hd":false},{"ind":30,"ty":"sh","ix":31,"ks":{"a":0,"k":{"i":[[0.381,0],[0.338,0.156],[0.199,0.298],[0,0.426],[-0.148,0.233],[-0.247,0.133],[-0.298,0.066],[-0.304,0.04],[-0.247,0.026],[-0.114,0.065],[0,0.162],[0,0],[0.231,0.233],[0.463,0],[0.272,-0.211],[0.111,-0.239],[0,0],[-0.284,0.222],[-0.338,0.088],[-0.33,0],[-0.272,-0.052],[-0.256,-0.153],[-0.171,-0.31],[0,-0.52],[0,0],[0,0],[0,0],[0,0],[0.159,-0.162],[0.264,-0.114]],"o":[[-0.414,0],[-0.338,-0.159],[-0.199,-0.302],[0,-0.375],[0.148,-0.236],[0.247,-0.134],[0.302,-0.068],[0.398,-0.051],[0.25,-0.028],[0.116,-0.066],[0,0],[0,-0.421],[-0.227,-0.233],[-0.48,0],[-0.273,0.21],[0,0],[0.17,-0.398],[0.287,-0.224],[0.341,-0.091],[0.21,0],[0.276,0.048],[0.259,0.154],[0.17,0.309],[0,0],[0,0],[0,0],[0,0],[-0.068,0.142],[-0.16,0.162],[-0.265,0.113]],"v":[[20.622,-2.559],[19.493,-2.794],[18.689,-3.48],[18.389,-4.57],[18.611,-5.482],[19.204,-6.036],[20.021,-6.335],[20.93,-6.497],[21.896,-6.613],[22.443,-6.753],[22.618,-7.094],[22.618,-7.128],[22.271,-8.107],[21.236,-8.458],[20.107,-8.141],[19.532,-7.469],[18.577,-7.809],[19.26,-8.738],[20.197,-9.208],[21.202,-9.344],[21.926,-9.266],[22.723,-8.965],[23.368,-8.27],[23.622,-7.025],[23.622,-2.712],[22.618,-2.712],[22.618,-3.6],[22.566,-3.6],[22.225,-3.143],[21.59,-2.73]],"c":true},"ix":2},"nm":"Path 31","mn":"ADBE Vector Shape - Group","hd":false},{"ind":31,"ty":"sh","ix":32,"ks":{"a":0,"k":{"i":[[0.483,0],[0.443,0.29],[0.239,0.508],[0,0.653],[-0.245,0.509],[-0.44,0.286],[-0.591,0],[-0.369,-0.171],[-0.236,-0.306],[-0.057,-0.409],[0,0],[0.264,0.23],[0.443,0],[0.295,-0.204],[0.165,-0.37],[0,-0.494],[-0.16,-0.375],[-0.292,-0.208],[-0.398,0],[-0.213,0.091],[-0.148,0.171],[-0.062,0.239],[0,0],[0.225,-0.31],[0.367,-0.182]],"o":[[-0.613,0],[-0.443,-0.29],[-0.238,-0.509],[0,-0.665],[0.247,-0.511],[0.443,-0.29],[0.46,0],[0.37,0.17],[0.236,0.307],[0,0],[-0.076,-0.298],[-0.261,-0.233],[-0.392,0],[-0.293,0.202],[-0.162,0.366],[0,0.506],[0.161,0.375],[0.296,0.207],[0.262,0],[0.213,-0.091],[0.148,-0.17],[0,0],[-0.057,0.387],[-0.221,0.306],[-0.364,0.179]],"v":[[14.652,-2.577],[13.068,-3.011],[12.045,-4.208],[11.687,-5.952],[12.053,-7.712],[13.085,-8.909],[14.635,-9.344],[15.88,-9.087],[16.788,-8.372],[17.227,-7.299],[16.221,-7.299],[15.71,-8.09],[14.652,-8.441],[13.622,-8.133],[12.936,-7.277],[12.693,-5.986],[12.932,-4.665],[13.613,-3.79],[14.652,-3.48],[15.365,-3.617],[15.906,-4.008],[16.221,-4.622],[17.227,-4.622],[16.805,-3.577],[15.923,-2.844]],"c":true},"ix":2},"nm":"Path 32","mn":"ADBE Vector Shape - Group","hd":false},{"ind":32,"ty":"sh","ix":33,"ks":{"a":0,"k":{"i":[[0,-0.381],[0,0],[0,0],[0,0],[0,0],[0,0],[0,0],[-0.306,0.199],[-0.514,0],[-0.335,-0.179],[-0.185,-0.366],[0,-0.562],[0,0],[0,0],[0,0],[0.27,0.284],[0.475,0],[0.261,-0.139],[0.151,-0.266]],"o":[[0,0],[0,0],[0,0],[0,0],[0,0],[0,0],[0.154,-0.338],[0.31,-0.201],[0.446,0],[0.335,0.177],[0.187,0.364],[0,0],[0,0],[0,0],[0,-0.52],[-0.267,-0.287],[-0.329,0],[-0.258,0.139],[-0.147,0.268]],"v":[[2.535,-6.65],[2.535,-2.712],[1.529,-2.712],[1.529,-11.441],[2.535,-11.441],[2.535,-8.236],[2.62,-8.236],[3.31,-9.042],[4.546,-9.344],[5.717,-9.076],[6.497,-8.262],[6.779,-6.872],[6.779,-2.712],[5.773,-2.712],[5.773,-6.803],[5.368,-8.01],[4.256,-8.441],[3.37,-8.232],[2.756,-7.622]],"c":true},"ix":2},"nm":"Path 33","mn":"ADBE Vector Shape - Group","hd":false},{"ind":33,"ty":"sh","ix":34,"ks":{"a":0,"k":{"i":[[0.483,0],[0.443,0.29],[0.239,0.508],[0,0.653],[-0.245,0.509],[-0.44,0.286],[-0.591,0],[-0.369,-0.171],[-0.236,-0.306],[-0.057,-0.409],[0,0],[0.264,0.23],[0.443,0],[0.295,-0.204],[0.165,-0.37],[0,-0.494],[-0.16,-0.375],[-0.292,-0.208],[-0.398,0],[-0.213,0.091],[-0.148,0.171],[-0.062,0.239],[0,0],[0.225,-0.31],[0.367,-0.182]],"o":[[-0.613,0],[-0.443,-0.29],[-0.238,-0.509],[0,-0.665],[0.247,-0.511],[0.443,-0.29],[0.46,0],[0.37,0.17],[0.236,0.307],[0,0],[-0.076,-0.298],[-0.261,-0.233],[-0.392,0],[-0.293,0.202],[-0.162,0.366],[0,0.506],[0.162,0.375],[0.296,0.207],[0.262,0],[0.213,-0.091],[0.148,-0.17],[0,0],[-0.057,0.387],[-0.221,0.306],[-0.364,0.179]],"v":[[-2.516,-2.577],[-4.1,-3.011],[-5.124,-4.208],[-5.482,-5.952],[-5.115,-7.712],[-4.083,-8.909],[-2.533,-9.344],[-1.288,-9.087],[-0.38,-8.372],[0.059,-7.299],[-0.947,-7.299],[-1.458,-8.09],[-2.516,-8.441],[-3.546,-8.133],[-4.232,-7.277],[-4.475,-5.986],[-4.236,-4.665],[-3.555,-3.79],[-2.516,-3.48],[-1.803,-3.617],[-1.262,-4.008],[-0.947,-4.622],[0.059,-4.622],[-0.363,-3.577],[-1.245,-2.844]],"c":true},"ix":2},"nm":"Path 34","mn":"ADBE Vector Shape - Group","hd":false},{"ind":34,"ty":"sh","ix":35,"ks":{"a":0,"k":{"i":[[0,0],[0,0],[0,0],[-0.082,-0.142],[-0.13,-0.048],[-0.148,0],[-0.071,0.012],[-0.042,0.009],[0,0],[0.123,-0.025],[0.187,0],[0.272,0.122],[0.179,0.25],[0,0.381]],"o":[[0,0],[0,0],[0,0.284],[0.086,0.139],[0.134,0.045],[0.111,0],[0.071,-0.014],[0,0],[-0.068,0.026],[-0.122,0.029],[-0.284,0],[-0.27,-0.123],[-0.176,-0.25],[0,0]],"v":[[-9.021,-10.827],[-8.014,-10.827],[-8.014,-4.587],[-7.891,-3.949],[-7.568,-3.667],[-7.146,-3.6],[-6.872,-3.617],[-6.702,-3.65],[-6.497,-2.747],[-6.783,-2.671],[-7.247,-2.628],[-8.083,-2.811],[-8.757,-3.37],[-9.021,-4.316]],"c":true},"ix":2},"nm":"Path 35","mn":"ADBE Vector Shape - Group","hd":false},{"ind":35,"ty":"sh","ix":36,"ks":{"a":0,"k":{"i":[[0,0],[0,0],[0,0],[0,0]],"o":[[0,0],[0,0],[0,0],[0,0]],"v":[[-6.617,-8.406],[-10.008,-8.406],[-10.008,-9.258],[-6.617,-9.258]],"c":true},"ix":2},"nm":"Path 36","mn":"ADBE Vector Shape - Group","hd":false},{"ind":36,"ty":"sh","ix":37,"ks":{"a":0,"k":{"i":[[0,0]],"o":[[0,0]],"v":[[-6.617,-9.258]],"c":false},"ix":2},"nm":"Path 37","mn":"ADBE Vector Shape - Group","hd":false},{"ind":37,"ty":"sh","ix":38,"ks":{"a":0,"k":{"i":[[-0.401,0],[-0.273,0.157],[-0.14,0.247],[0,0.273],[0,0],[0.144,-0.042],[0.188,-0.031],[0.176,-0.023],[0.108,-0.014],[0.227,-0.077],[0.139,-0.151],[0,-0.256],[-0.259,-0.179]],"o":[[0.398,0],[0.275,-0.156],[0.142,-0.247],[0,0],[-0.043,0.051],[-0.143,0.04],[-0.184,0.028],[-0.173,0.02],[-0.261,0.034],[-0.224,0.074],[-0.137,0.147],[0,0.349],[0.261,0.176]],"v":[[-14.146,-3.462],[-13.139,-3.697],[-12.518,-4.303],[-12.305,-5.083],[-12.305,-6.003],[-12.585,-5.863],[-13.081,-5.756],[-13.622,-5.678],[-14.044,-5.628],[-14.777,-5.462],[-15.322,-5.124],[-15.527,-4.52],[-15.139,-3.727]],"c":true},"ix":2},"nm":"Path 38","mn":"ADBE Vector Shape - Group","hd":false},{"ind":38,"ty":"sh","ix":39,"ks":{"a":0,"k":{"i":[[0.381,0],[0.338,0.156],[0.199,0.298],[0,0.426],[-0.148,0.233],[-0.247,0.133],[-0.299,0.066],[-0.304,0.04],[-0.248,0.026],[-0.114,0.065],[0,0.162],[0,0],[0.23,0.233],[0.463,0],[0.273,-0.211],[0.11,-0.239],[0,0],[-0.284,0.222],[-0.338,0.088],[-0.33,0],[-0.272,-0.052],[-0.255,-0.153],[-0.171,-0.31],[0,-0.52],[0,0],[0,0],[0,0],[0,0],[0.159,-0.162],[0.264,-0.114]],"o":[[-0.414,0],[-0.338,-0.159],[-0.199,-0.302],[0,-0.375],[0.148,-0.236],[0.248,-0.134],[0.301,-0.068],[0.398,-0.051],[0.25,-0.028],[0.117,-0.066],[0,0],[0,-0.421],[-0.228,-0.233],[-0.48,0],[-0.273,0.21],[0,0],[0.17,-0.398],[0.287,-0.224],[0.341,-0.091],[0.21,0],[0.276,0.048],[0.259,0.154],[0.17,0.309],[0,0],[0,0],[0,0],[0,0],[-0.069,0.142],[-0.159,0.162],[-0.264,0.113]],"v":[[-14.299,-2.559],[-15.428,-2.794],[-16.234,-3.48],[-16.533,-4.57],[-16.311,-5.482],[-15.719,-6.036],[-14.9,-6.335],[-13.993,-6.497],[-13.025,-6.613],[-12.48,-6.753],[-12.305,-7.094],[-12.305,-7.128],[-12.65,-8.107],[-13.686,-8.458],[-14.814,-8.141],[-15.389,-7.469],[-16.344,-7.809],[-15.663,-8.738],[-14.725,-9.208],[-13.719,-9.344],[-12.995,-9.266],[-12.199,-8.965],[-11.555,-8.27],[-11.299,-7.025],[-11.299,-2.712],[-12.305,-2.712],[-12.305,-3.6],[-12.355,-3.6],[-12.697,-3.143],[-13.331,-2.73]],"c":true},"ix":2},"nm":"Path 39","mn":"ADBE Vector Shape - Group","hd":false},{"ind":39,"ty":"sh","ix":40,"ks":{"a":0,"k":{"i":[[0,0],[0,0],[0,0],[0,0],[0,0],[-0.313,0.202],[-0.392,0],[-0.111,-0.003],[-0.057,-0.006],[0,0],[0.122,0.017],[0.133,0],[0.25,-0.134],[0.145,-0.233],[0,-0.296],[0,0]],"o":[[0,0],[0,0],[0,0],[0,0],[0.12,-0.324],[0.312,-0.201],[0.074,0],[0.111,0.003],[0,0],[-0.034,-0.009],[-0.12,-0.02],[-0.319,0],[-0.247,0.13],[-0.142,0.23],[0,0],[0,0]],"v":[[-20.691,-2.712],[-20.691,-9.258],[-19.719,-9.258],[-19.719,-8.27],[-19.65,-8.27],[-19.003,-9.059],[-17.945,-9.361],[-17.669,-9.357],[-17.417,-9.344],[-17.417,-8.32],[-17.652,-8.359],[-18.031,-8.389],[-18.883,-8.189],[-19.471,-7.643],[-19.684,-6.855],[-19.684,-2.712]],"c":true},"ix":2},"nm":"Path 40","mn":"ADBE Vector Shape - Group","hd":false},{"ind":40,"ty":"sh","ix":41,"ks":{"a":0,"k":{"i":[[0.483,0],[0.443,0.29],[0.239,0.508],[0,0.653],[-0.244,0.509],[-0.44,0.286],[-0.591,0],[-0.37,-0.171],[-0.235,-0.306],[-0.057,-0.409],[0,0],[0.264,0.23],[0.444,0],[0.296,-0.204],[0.165,-0.37],[0,-0.494],[-0.159,-0.375],[-0.293,-0.208],[-0.397,0],[-0.213,0.091],[-0.147,0.171],[-0.063,0.239],[0,0],[0.225,-0.31],[0.367,-0.182]],"o":[[-0.613,0],[-0.443,-0.29],[-0.238,-0.509],[0,-0.665],[0.247,-0.511],[0.443,-0.29],[0.461,0],[0.369,0.17],[0.236,0.307],[0,0],[-0.077,-0.298],[-0.261,-0.233],[-0.392,0],[-0.292,0.202],[-0.162,0.366],[0,0.506],[0.162,0.375],[0.295,0.207],[0.262,0],[0.213,-0.091],[0.148,-0.17],[0,0],[-0.057,0.387],[-0.221,0.306],[-0.363,0.179]],"v":[[-24.734,-2.577],[-26.32,-3.011],[-27.342,-4.208],[-27.699,-5.952],[-27.333,-7.712],[-26.303,-8.909],[-24.751,-9.344],[-23.507,-9.087],[-22.6,-8.372],[-22.161,-7.299],[-23.165,-7.299],[-23.678,-8.09],[-24.734,-8.441],[-25.766,-8.133],[-26.451,-7.277],[-26.695,-5.986],[-26.456,-4.665],[-25.773,-3.79],[-24.734,-3.48],[-24.023,-3.617],[-23.482,-4.008],[-23.165,-4.622],[-22.161,-4.622],[-22.583,-3.577],[-23.464,-2.844]],"c":true},"ix":2},"nm":"Path 41","mn":"ADBE Vector Shape - Group","hd":false},{"ind":41,"ty":"sh","ix":42,"ks":{"a":0,"k":{"i":[[-0.156,-0.466],[0,0],[0.111,0.142],[0.188,0.094],[0.293,0],[0.267,-0.184],[0,-0.281],[-0.182,-0.145],[-0.386,-0.096],[0,0],[-0.287,-0.293],[0,-0.458],[0.215,-0.295],[0.383,-0.17],[0.508,0],[0.437,0.29],[0.116,0.557],[0,0],[-0.253,-0.176],[-0.412,0],[-0.276,0.199],[0,0.281],[0.159,0.153],[0.33,0.077],[0,0],[0.281,0.299],[0,0.452],[-0.208,0.284],[-0.361,0.162],[-0.46,0],[-0.369,-0.284]],"o":[[0,0],[-0.057,-0.151],[-0.108,-0.145],[-0.187,-0.094],[-0.401,0],[-0.265,0.182],[0,0.25],[0.182,0.145],[0,0],[0.585,0.142],[0.287,0.29],[0,0.375],[-0.214,0.296],[-0.384,0.171],[-0.668,0],[-0.438,-0.29],[0,0],[0.09,0.352],[0.256,0.176],[0.468,0],[0.278,-0.201],[0,-0.227],[-0.159,-0.156],[0,0],[-0.599,-0.142],[-0.278,-0.301],[0,-0.369],[0.21,-0.284],[0.364,-0.162],[0.648,0],[0.373,0.284]],"v":[[-29.027,-7.792],[-29.93,-7.536],[-30.182,-7.975],[-30.624,-8.333],[-31.344,-8.475],[-32.346,-8.197],[-32.742,-7.503],[-32.469,-6.911],[-31.617,-6.549],[-30.645,-6.309],[-29.337,-5.658],[-28.908,-4.536],[-29.23,-3.531],[-30.126,-2.833],[-31.464,-2.577],[-33.122,-3.011],[-33.952,-4.281],[-32.997,-4.52],[-32.482,-3.727],[-31.48,-3.462],[-30.365,-3.762],[-29.947,-4.486],[-30.186,-5.057],[-30.919,-5.406],[-32.01,-5.661],[-33.331,-6.322],[-33.747,-7.452],[-33.436,-8.432],[-32.581,-9.1],[-31.344,-9.344],[-29.82,-8.917]],"c":true},"ix":2},"nm":"Path 42","mn":"ADBE Vector Shape - Group","hd":false},{"ind":42,"ty":"sh","ix":43,"ks":{"a":0,"k":{"i":[[0,0],[0,0],[0,0],[0,0],[0,0],[-0.312,0.202],[-0.392,0],[-0.11,-0.003],[-0.057,-0.006],[0,0],[0.123,0.017],[0.134,0],[0.25,-0.134],[0.145,-0.233],[0,-0.296],[0,0]],"o":[[0,0],[0,0],[0,0],[0,0],[0.119,-0.324],[0.313,-0.201],[0.074,0],[0.111,0.003],[0,0],[-0.034,-0.009],[-0.119,-0.02],[-0.318,0],[-0.247,0.13],[-0.142,0.23],[0,0],[0,0]],"v":[[-41.503,-2.712],[-41.503,-9.258],[-40.531,-9.258],[-40.531,-8.27],[-40.462,-8.27],[-39.816,-9.059],[-38.758,-9.361],[-38.482,-9.357],[-38.229,-9.344],[-38.229,-8.32],[-38.464,-8.359],[-38.844,-8.389],[-39.695,-8.189],[-40.283,-7.643],[-40.497,-6.855],[-40.497,-2.712]],"c":true},"ix":2},"nm":"Path 43","mn":"ADBE Vector Shape - Group","hd":false},{"ind":43,"ty":"sh","ix":44,"ks":{"a":0,"k":{"i":[[0,0.409],[0,0],[0,0],[0,0],[0,0],[0,0],[0,0],[0.324,-0.233],[0.494,0],[0.318,0.179],[0.182,0.364],[0,0.557],[0,0],[0,0],[0,0],[-0.267,-0.284],[-0.418,0],[-0.259,0.127],[-0.176,0.265]],"o":[[0,0],[0,0],[0,0],[0,0],[0,0],[0,0],[-0.153,0.332],[-0.324,0.23],[-0.409,0],[-0.318,-0.181],[-0.182,-0.366],[0,0],[0,0],[0,0],[0,0.477],[0.27,0.284],[0.25,0],[0.261,-0.128],[0.179,-0.264]],"v":[[-44.35,-5.389],[-44.35,-9.258],[-43.344,-9.258],[-43.344,-2.712],[-44.35,-2.712],[-44.35,-3.82],[-44.419,-3.82],[-45.135,-2.973],[-46.361,-2.628],[-47.452,-2.896],[-48.202,-3.714],[-48.475,-5.1],[-48.475,-9.258],[-47.469,-9.258],[-47.469,-5.167],[-47.07,-4.025],[-46.038,-3.6],[-45.275,-3.79],[-44.618,-4.38]],"c":true},"ix":2},"nm":"Path 44","mn":"ADBE Vector Shape - Group","hd":false},{"ind":44,"ty":"sh","ix":45,"ks":{"a":0,"k":{"i":[[-0.449,0],[-0.29,0.231],[-0.14,0.375],[0,0.438],[0.139,0.378],[0.29,0.233],[0.449,0],[0.29,-0.233],[0.139,-0.378],[0,-0.437],[-0.139,-0.375],[-0.289,-0.23]],"o":[[0.449,0],[0.29,-0.23],[0.139,-0.375],[0,-0.437],[-0.14,-0.378],[-0.29,-0.233],[-0.449,0],[-0.289,0.233],[-0.139,0.378],[0,0.438],[0.139,0.375],[0.29,0.231]],"v":[[-52.977,-3.48],[-51.868,-3.826],[-51.225,-4.732],[-51.016,-5.952],[-51.225,-7.174],[-51.868,-8.09],[-52.977,-8.441],[-54.085,-8.09],[-54.728,-7.174],[-54.937,-5.952],[-54.728,-4.732],[-54.085,-3.826]],"c":true},"ix":2},"nm":"Path 45","mn":"ADBE Vector Shape - Group","hd":false},{"ind":45,"ty":"sh","ix":46,"ks":{"a":0,"k":{"i":[[0.591,0],[0.446,0.281],[0.25,0.505],[0,0.676],[-0.247,0.509],[-0.443,0.281],[-0.591,0],[-0.443,-0.281],[-0.247,-0.508],[0,-0.682],[0.25,-0.506],[0.446,-0.281]],"o":[[-0.591,0],[-0.443,-0.281],[-0.247,-0.506],[0,-0.682],[0.25,-0.508],[0.446,-0.281],[0.591,0],[0.446,0.281],[0.25,0.509],[0,0.676],[-0.247,0.505],[-0.443,0.281]],"v":[[-52.977,-2.577],[-54.531,-2.999],[-55.572,-4.178],[-55.943,-5.952],[-55.572,-7.738],[-54.531,-8.921],[-52.977,-9.344],[-51.426,-8.921],[-50.385,-7.738],[-50.01,-5.952],[-50.385,-4.178],[-51.426,-2.999]],"c":true},"ix":2},"nm":"Path 46","mn":"ADBE Vector Shape - Group","hd":false},{"ind":46,"ty":"sh","ix":47,"ks":{"a":0,"k":{"i":[[0,0],[0,0],[0,0],[0,0],[0,0],[0,0],[0,0],[0,0],[0,0],[0,0]],"o":[[0,0],[0,0],[0,0],[0,0],[0,0],[0,0],[0,0],[0,0],[0,0],[0,0]],"v":[[-63.303,-11.441],[-62.094,-11.441],[-59.674,-7.367],[-59.57,-7.367],[-57.15,-11.441],[-55.941,-11.441],[-59.094,-6.309],[-59.094,-2.712],[-60.15,-2.712],[-60.15,-6.309]],"c":true},"ix":2},"nm":"Path 47","mn":"ADBE Vector Shape - Group","hd":false},{"ty":"mm","mm":1,"nm":"Merge Paths 1","mn":"ADBE Vector Filter - Merge","hd":false},{"ty":"fl","c":{"a":0,"k":[1,1,1,1],"ix":4},"o":{"a":0,"k":100,"ix":5},"r":1,"bm":0,"nm":"Fill 1","mn":"ADBE Vector Graphic - Fill","hd":false},{"ty":"tr","p":{"a":0,"k":[128.611,37.713],"ix":2},"a":{"a":0,"k":[0,0],"ix":1},"s":{"a":0,"k":[100,100],"ix":3},"r":{"a":0,"k":0,"ix":6},"o":{"a":0,"k":100,"ix":7},"sk":{"a":0,"k":0,"ix":4},"sa":{"a":0,"k":0,"ix":5},"nm":"Transform"}],"nm":"Group 1","np":51,"cix":2,"bm":0,"ix":1,"mn":"ADBE Vector Group","hd":false}],"ip":0,"op":1694,"st":0,"ct":1,"bm":0},{"ddd":0,"ind":6,"ty":4,"nm":"Layer 7 Outlines","parent":1,"sr":1,"ks":{"o":{"a":0,"k":100,"ix":11},"r":{"a":0,"k":0,"ix":10},"p":{"a":0,"k":[-227.5,210,0],"ix":2,"l":2},"a":{"a":0,"k":[111,38.5,0],"ix":1,"l":2},"s":{"a":0,"k":[500,500,100],"ix":6,"l":2}},"ao":0,"shapes":[{"ty":"gr","it":[{"ind":0,"ty":"sh","ix":1,"ks":{"a":0,"k":{"i":[[-8.008,0],[0,0],[0,-8.008],[0,0],[8.008,0],[0,0],[0,8.008],[0,0]],"o":[[0,0],[8.008,0],[0,0],[0,8.008],[0,0],[-8.008,0],[0,0],[0,-8.008]],"v":[[-77,-24],[77,-24],[91.5,-9.5],[91.5,9.5],[77,24],[-77,24],[-91.5,9.5],[-91.5,-9.5]],"c":true},"ix":2},"nm":"Path 1","mn":"ADBE Vector Shape - Group","hd":false},{"ty":"st","c":{"a":0,"k":[1,1,1,1],"ix":3},"o":{"a":0,"k":100,"ix":4},"w":{"a":0,"k":1,"ix":5},"lc":1,"lj":1,"ml":4,"bm":0,"nm":"Stroke 1","mn":"ADBE Vector Graphic - Stroke","hd":false},{"ty":"tr","p":{"a":0,"k":[115,37.5],"ix":2},"a":{"a":0,"k":[0,0],"ix":1},"s":{"a":0,"k":[100,100],"ix":3},"r":{"a":0,"k":0,"ix":6},"o":{"a":0,"k":100,"ix":7},"sk":{"a":0,"k":0,"ix":4},"sa":{"a":0,"k":0,"ix":5},"nm":"Transform"}],"nm":"Group 1","np":2,"cix":2,"bm":0,"ix":1,"mn":"ADBE Vector Group","hd":false}],"ip":0,"op":1694,"st":0,"ct":1,"bm":0},{"ddd":0,"ind":7,"ty":4,"nm":"Layer 8 Outlines","parent":1,"sr":1,"ks":{"o":{"a":0,"k":100,"ix":11},"r":{"a":0,"k":0,"ix":10},"p":{"a":0,"k":[-227.5,210,0],"ix":2,"l":2},"a":{"a":0,"k":[111,38.5,0],"ix":1,"l":2},"s":{"a":0,"k":[500,500,100],"ix":6,"l":2}},"ao":0,"shapes":[{"ty":"gr","it":[{"ind":0,"ty":"sh","ix":1,"ks":{"a":0,"k":{"i":[[-8.284,0],[0,0],[0,-8.284],[0,0],[8.284,0],[0,0],[0,8.284],[0,0]],"o":[[0,0],[8.284,0],[0,0],[0,8.284],[0,0],[-8.284,0],[0,0],[0,-8.284]],"v":[[-77,-24.5],[77,-24.5],[92,-9.5],[92,9.5],[77,24.5],[-77,24.5],[-92,9.5],[-92,-9.5]],"c":true},"ix":2},"nm":"Path 1","mn":"ADBE Vector Shape - Group","hd":false},{"ty":"fl","c":{"a":0,"k":[0,0,0,1],"ix":4},"o":{"a":0,"k":100,"ix":5},"r":1,"bm":0,"nm":"Fill 1","mn":"ADBE Vector Graphic - Fill","hd":false},{"ty":"tr","p":{"a":0,"k":[115,37.5],"ix":2},"a":{"a":0,"k":[0,0],"ix":1},"s":{"a":0,"k":[100,100],"ix":3},"r":{"a":0,"k":0,"ix":6},"o":{"a":0,"k":100,"ix":7},"sk":{"a":0,"k":0,"ix":4},"sa":{"a":0,"k":0,"ix":5},"nm":"Transform"}],"nm":"Group 1","np":4,"cix":2,"bm":0,"ix":1,"mn":"ADBE Vector Group","hd":false}],"ip":0,"op":1694,"st":0,"ct":1,"bm":0}]}],"layers":[{"ddd":0,"ind":1,"ty":0,"nm":"Tooltip message_1","refId":"comp_0","sr":1,"ks":{"o":{"a":0,"k":100,"ix":11},"r":{"a":0,"k":0,"ix":10},"p":{"a":0,"k":[227.878,109.682,0],"ix":2,"l":2},"a":{"a":0,"k":[144,50,0],"ix":1,"l":2},"s":{"a":0,"k":[100,100,100],"ix":6,"l":2}},"ao":0,"w":288,"h":100,"ip":33,"op":101,"st":33,"ct":1,"bm":0},{"ddd":0,"ind":2,"ty":4,"nm":"Layer 2 Outlines","sr":1,"ks":{"o":{"a":0,"k":100,"ix":11},"r":{"a":1,"k":[{"i":{"x":[0.833],"y":[0.833]},"o":{"x":[0.167],"y":[0.167]},"t":39,"s":[0]},{"i":{"x":[0.833],"y":[0.833]},"o":{"x":[0.167],"y":[0.167]},"t":42,"s":[13]},{"i":{"x":[0.833],"y":[0.833]},"o":{"x":[0.167],"y":[0.167]},"t":45,"s":[-18]},{"i":{"x":[0.833],"y":[0.833]},"o":{"x":[0.167],"y":[0.167]},"t":48,"s":[58]},{"t":53,"s":[0]}],"ix":10},"p":{"a":0,"k":[286.584,55.671,0],"ix":2,"l":2},"a":{"a":0,"k":[164.584,163.671,0],"ix":1,"l":2},"s":{"a":1,"k":[{"i":{"x":[0.667,0.667,0.667],"y":[1,1,1]},"o":{"x":[0.333,0.333,0.333],"y":[0,0,0]},"t":33,"s":[73,73,100]},{"i":{"x":[0.667,0.667,0.667],"y":[1,1,1]},"o":{"x":[0.333,0.333,0.333],"y":[0,0,0]},"t":36,"s":[90,90,100]},{"t":43,"s":[73,73,100]}],"ix":6,"l":2}},"ao":0,"shapes":[{"ty":"gr","it":[{"ty":"gr","it":[{"ind":0,"ty":"sh","ix":1,"ks":{"a":0,"k":{"i":[[0,0],[0,0],[0,0],[0,0],[0,0],[0,0],[0,0],[0,0],[0,0]],"o":[[0,0],[0,0],[0,0],[0,0],[0,0],[0,0],[0,0],[0,0],[0,0]],"v":[[-9.85,-6.445],[1.798,-8.747],[5.967,-5.371],[-0.935,-3.376],[9.85,-0.154],[-0.935,8.747],[-5.105,6.6],[0.934,1.689],[-9.85,0.768]],"c":true},"ix":2},"nm":"Path 1","mn":"ADBE Vector Shape - Group","hd":false},{"ty":"mm","mm":4,"nm":"Merge Paths 1","mn":"ADBE Vector Filter - Merge","hd":false},{"ty":"fl","c":{"a":0,"k":[1,0.941176530427,0.713725490196,1],"ix":4},"o":{"a":0,"k":100,"ix":5},"r":1,"bm":0,"nm":"Fill 1","mn":"ADBE Vector Graphic - Fill","hd":false},{"ty":"tr","p":{"a":0,"k":[165.624,163.975],"ix":2},"a":{"a":0,"k":[0,0],"ix":1},"s":{"a":0,"k":[100,100],"ix":3},"r":{"a":0,"k":0,"ix":6},"o":{"a":0,"k":100,"ix":7},"sk":{"a":0,"k":0,"ix":4},"sa":{"a":0,"k":0,"ix":5},"nm":"Transform"}],"nm":"Group 1","np":3,"cix":2,"bm":0,"ix":1,"mn":"ADBE Vector Group","hd":false},{"ty":"gr","it":[{"ind":0,"ty":"sh","ix":1,"ks":{"a":0,"k":{"i":[[-5.87,5.87],[5.87,5.87],[5.87,-5.87],[-5.87,-5.87]],"o":[[5.87,-5.87],[-5.87,-5.87],[-5.87,5.87],[5.87,5.87]],"v":[[10.629,10.629],[10.629,-10.629],[-10.628,-10.629],[-10.628,10.629]],"c":true},"ix":2},"nm":"Path 1","mn":"ADBE Vector Shape - Group","hd":false},{"ty":"mm","mm":4,"nm":"Merge Paths 1","mn":"ADBE Vector Filter - Merge","hd":false},{"ty":"fl","c":{"a":0,"k":[1,0.674509803922,0,1],"ix":4},"o":{"a":0,"k":100,"ix":5},"r":1,"bm":0,"nm":"Fill 1","mn":"ADBE Vector Graphic - Fill","hd":false},{"ty":"tr","p":{"a":0,"k":[164.583,163.671],"ix":2},"a":{"a":0,"k":[0,0],"ix":1},"s":{"a":0,"k":[100,100],"ix":3},"r":{"a":0,"k":0,"ix":6},"o":{"a":0,"k":100,"ix":7},"sk":{"a":0,"k":0,"ix":4},"sa":{"a":0,"k":0,"ix":5},"nm":"Transform"}],"nm":"Group 4","np":3,"cix":2,"bm":0,"ix":2,"mn":"ADBE Vector Group","hd":false},{"ty":"gr","it":[{"ind":0,"ty":"sh","ix":1,"ks":{"a":0,"k":{"i":[[-11.457,0],[0,11.457],[11.457,0],[0,-11.457]],"o":[[11.457,0],[0,-11.457],[-11.457,0],[0,11.457]],"v":[[0.001,20.745],[20.745,0],[0.001,-20.745],[-20.744,0]],"c":true},"ix":2},"nm":"Path 1","mn":"ADBE Vector Shape - Group","hd":false},{"ty":"mm","mm":4,"nm":"Merge Paths 1","mn":"ADBE Vector Filter - Merge","hd":false},{"ty":"fl","c":{"a":0,"k":[0.996078491211,0.831372608858,0.145098039216,1],"ix":4},"o":{"a":0,"k":100,"ix":5},"r":1,"bm":0,"nm":"Fill 1","mn":"ADBE Vector Graphic - Fill","hd":false},{"ty":"tr","p":{"a":0,"k":[164.583,163.671],"ix":2},"a":{"a":0,"k":[0,0],"ix":1},"s":{"a":0,"k":[100,100],"ix":3},"r":{"a":0,"k":0,"ix":6},"o":{"a":0,"k":100,"ix":7},"sk":{"a":0,"k":0,"ix":4},"sa":{"a":0,"k":0,"ix":5},"nm":"Transform"}],"nm":"Group 6","np":3,"cix":2,"bm":0,"ix":3,"mn":"ADBE Vector Group","hd":false},{"ty":"gr","it":[{"ind":0,"ty":"sh","ix":1,"ks":{"a":0,"k":{"i":[[-11.758,0],[0,11.758],[11.757,0],[0,-11.758]],"o":[[11.757,0],[0,-11.758],[-11.758,0],[0,11.758]],"v":[[0,21.289],[21.289,0],[0,-21.289],[-21.289,0]],"c":true},"ix":2},"nm":"Path 1","mn":"ADBE Vector Shape - Group","hd":false},{"ty":"mm","mm":4,"nm":"Merge Paths 1","mn":"ADBE Vector Filter - Merge","hd":false},{"ty":"fl","c":{"a":0,"k":[0.996078491211,0.894117706897,0.458823559331,1],"ix":4},"o":{"a":0,"k":100,"ix":5},"r":1,"bm":0,"nm":"Fill 1","mn":"ADBE Vector Graphic - Fill","hd":false},{"ty":"tr","p":{"a":0,"k":[164.584,163.671],"ix":2},"a":{"a":0,"k":[0,0],"ix":1},"s":{"a":0,"k":[100,100],"ix":3},"r":{"a":0,"k":0,"ix":6},"o":{"a":0,"k":100,"ix":7},"sk":{"a":0,"k":0,"ix":4},"sa":{"a":0,"k":0,"ix":5},"nm":"Transform"}],"nm":"Group 7","np":3,"cix":2,"bm":0,"ix":4,"mn":"ADBE Vector Group","hd":false},{"ty":"tr","p":{"a":0,"k":[164.584,163.671],"ix":2},"a":{"a":0,"k":[164.584,163.671],"ix":1},"s":{"a":0,"k":[100,100],"ix":3},"r":{"a":0,"k":0,"ix":6},"o":{"a":0,"k":100,"ix":7},"sk":{"a":0,"k":0,"ix":4},"sa":{"a":0,"k":0,"ix":5},"nm":"Transform"}],"nm":"Group 1","np":4,"cix":2,"bm":0,"ix":1,"mn":"ADBE Vector Group","hd":false}],"ip":0,"op":101,"st":0,"ct":1,"bm":0},{"ddd":0,"ind":3,"ty":4,"nm":"Layer 2 Outlines 2","sr":1,"ks":{"o":{"a":0,"k":100,"ix":11},"r":{"a":1,"k":[{"i":{"x":[0.667],"y":[1]},"o":{"x":[0.333],"y":[0]},"t":27,"s":[0]},{"i":{"x":[0.667],"y":[1]},"o":{"x":[0.333],"y":[0]},"t":30,"s":[13]},{"i":{"x":[0.667],"y":[1]},"o":{"x":[0.333],"y":[0]},"t":31.909,"s":[-18]},{"i":{"x":[0.667],"y":[1]},"o":{"x":[0.333],"y":[0]},"t":33.818,"s":[58]},{"t":37,"s":[0]}],"ix":10},"p":{"a":1,"k":[{"i":{"x":0.667,"y":1},"o":{"x":0.333,"y":0},"t":27,"s":[180.158,385.63,0],"to":[-191.756,-487.155,0],"ti":[0,0,0]},{"t":37,"s":[286.584,55.671,0]}],"ix":2,"l":2},"a":{"a":0,"k":[164.584,163.671,0],"ix":1,"l":2},"s":{"a":1,"k":[{"i":{"x":[0.667,0.667,0.667],"y":[1,1,1]},"o":{"x":[0.333,0.333,0.333],"y":[0,0,0]},"t":20,"s":[0,0,100]},{"i":{"x":[0.667,0.667,0.667],"y":[1,1,1]},"o":{"x":[0.333,0.333,0.333],"y":[0,0,0]},"t":24,"s":[107,107,100]},{"i":{"x":[0.667,0.667,0.667],"y":[1,1,1]},"o":{"x":[0.333,0.333,0.333],"y":[0,0,0]},"t":27,"s":[73,73,100]},{"i":{"x":[0.667,0.667,0.667],"y":[1,1,1]},"o":{"x":[0.333,0.333,0.333],"y":[0,0,0]},"t":30,"s":[80,80,100]},{"i":{"x":[0.667,0.667,0.667],"y":[1,1,1]},"o":{"x":[0.333,0.333,0.333],"y":[0,0,0]},"t":31.909,"s":[85,85,100]},{"i":{"x":[0.667,0.667,0.667],"y":[1,1,1]},"o":{"x":[0.333,0.333,0.333],"y":[0,0,0]},"t":33.818,"s":[90,90,100]},{"t":37,"s":[73,73,100]}],"ix":6,"l":2}},"ao":0,"shapes":[{"ty":"gr","it":[{"ty":"gr","it":[{"ind":0,"ty":"sh","ix":1,"ks":{"a":0,"k":{"i":[[0,0],[0,0],[0,0],[0,0],[0,0],[0,0],[0,0],[0,0],[0,0]],"o":[[0,0],[0,0],[0,0],[0,0],[0,0],[0,0],[0,0],[0,0],[0,0]],"v":[[-9.85,-6.445],[1.798,-8.747],[5.967,-5.371],[-0.935,-3.376],[9.85,-0.154],[-0.935,8.747],[-5.105,6.6],[0.934,1.689],[-9.85,0.768]],"c":true},"ix":2},"nm":"Path 1","mn":"ADBE Vector Shape - Group","hd":false},{"ty":"mm","mm":4,"nm":"Merge Paths 1","mn":"ADBE Vector Filter - Merge","hd":false},{"ty":"fl","c":{"a":0,"k":[1,0.941176530427,0.713725490196,1],"ix":4},"o":{"a":0,"k":100,"ix":5},"r":1,"bm":0,"nm":"Fill 1","mn":"ADBE Vector Graphic - Fill","hd":false},{"ty":"tr","p":{"a":0,"k":[165.624,163.975],"ix":2},"a":{"a":0,"k":[0,0],"ix":1},"s":{"a":0,"k":[100,100],"ix":3},"r":{"a":0,"k":0,"ix":6},"o":{"a":0,"k":100,"ix":7},"sk":{"a":0,"k":0,"ix":4},"sa":{"a":0,"k":0,"ix":5},"nm":"Transform"}],"nm":"Group 1","np":3,"cix":2,"bm":0,"ix":1,"mn":"ADBE Vector Group","hd":false},{"ty":"gr","it":[{"ind":0,"ty":"sh","ix":1,"ks":{"a":0,"k":{"i":[[-5.87,5.87],[5.87,5.87],[5.87,-5.87],[-5.87,-5.87]],"o":[[5.87,-5.87],[-5.87,-5.87],[-5.87,5.87],[5.87,5.87]],"v":[[10.629,10.629],[10.629,-10.629],[-10.628,-10.629],[-10.628,10.629]],"c":true},"ix":2},"nm":"Path 1","mn":"ADBE Vector Shape - Group","hd":false},{"ty":"mm","mm":4,"nm":"Merge Paths 1","mn":"ADBE Vector Filter - Merge","hd":false},{"ty":"fl","c":{"a":0,"k":[1,0.674509803922,0,1],"ix":4},"o":{"a":0,"k":100,"ix":5},"r":1,"bm":0,"nm":"Fill 1","mn":"ADBE Vector Graphic - Fill","hd":false},{"ty":"tr","p":{"a":0,"k":[164.583,163.671],"ix":2},"a":{"a":0,"k":[0,0],"ix":1},"s":{"a":0,"k":[100,100],"ix":3},"r":{"a":0,"k":0,"ix":6},"o":{"a":0,"k":100,"ix":7},"sk":{"a":0,"k":0,"ix":4},"sa":{"a":0,"k":0,"ix":5},"nm":"Transform"}],"nm":"Group 4","np":3,"cix":2,"bm":0,"ix":2,"mn":"ADBE Vector Group","hd":false},{"ty":"gr","it":[{"ind":0,"ty":"sh","ix":1,"ks":{"a":0,"k":{"i":[[-11.457,0],[0,11.457],[11.457,0],[0,-11.457]],"o":[[11.457,0],[0,-11.457],[-11.457,0],[0,11.457]],"v":[[0.001,20.745],[20.745,0],[0.001,-20.745],[-20.744,0]],"c":true},"ix":2},"nm":"Path 1","mn":"ADBE Vector Shape - Group","hd":false},{"ty":"mm","mm":4,"nm":"Merge Paths 1","mn":"ADBE Vector Filter - Merge","hd":false},{"ty":"fl","c":{"a":0,"k":[0.996078491211,0.831372608858,0.145098039216,1],"ix":4},"o":{"a":0,"k":100,"ix":5},"r":1,"bm":0,"nm":"Fill 1","mn":"ADBE Vector Graphic - Fill","hd":false},{"ty":"tr","p":{"a":0,"k":[164.583,163.671],"ix":2},"a":{"a":0,"k":[0,0],"ix":1},"s":{"a":0,"k":[100,100],"ix":3},"r":{"a":0,"k":0,"ix":6},"o":{"a":0,"k":100,"ix":7},"sk":{"a":0,"k":0,"ix":4},"sa":{"a":0,"k":0,"ix":5},"nm":"Transform"}],"nm":"Group 6","np":3,"cix":2,"bm":0,"ix":3,"mn":"ADBE Vector Group","hd":false},{"ty":"gr","it":[{"ind":0,"ty":"sh","ix":1,"ks":{"a":0,"k":{"i":[[-11.758,0],[0,11.758],[11.757,0],[0,-11.758]],"o":[[11.757,0],[0,-11.758],[-11.758,0],[0,11.758]],"v":[[0,21.289],[21.289,0],[0,-21.289],[-21.289,0]],"c":true},"ix":2},"nm":"Path 1","mn":"ADBE Vector Shape - Group","hd":false},{"ty":"mm","mm":4,"nm":"Merge Paths 1","mn":"ADBE Vector Filter - Merge","hd":false},{"ty":"fl","c":{"a":0,"k":[0.996078491211,0.894117706897,0.458823559331,1],"ix":4},"o":{"a":0,"k":100,"ix":5},"r":1,"bm":0,"nm":"Fill 1","mn":"ADBE Vector Graphic - Fill","hd":false},{"ty":"tr","p":{"a":0,"k":[164.584,163.671],"ix":2},"a":{"a":0,"k":[0,0],"ix":1},"s":{"a":0,"k":[100,100],"ix":3},"r":{"a":0,"k":0,"ix":6},"o":{"a":0,"k":100,"ix":7},"sk":{"a":0,"k":0,"ix":4},"sa":{"a":0,"k":0,"ix":5},"nm":"Transform"}],"nm":"Group 7","np":3,"cix":2,"bm":0,"ix":4,"mn":"ADBE Vector Group","hd":false},{"ty":"tr","p":{"a":0,"k":[164.584,163.671],"ix":2},"a":{"a":0,"k":[164.584,163.671],"ix":1},"s":{"a":0,"k":[100,100],"ix":3},"r":{"a":0,"k":0,"ix":6},"o":{"a":0,"k":100,"ix":7},"sk":{"a":0,"k":0,"ix":4},"sa":{"a":0,"k":0,"ix":5},"nm":"Transform"}],"nm":"Group 1","np":4,"cix":2,"bm":0,"ix":1,"mn":"ADBE Vector Group","hd":false}],"ip":0,"op":101,"st":0,"ct":1,"bm":0},{"ddd":0,"ind":4,"ty":4,"nm":"Layer 8 Outlines","sr":1,"ks":{"o":{"a":0,"k":100,"ix":11},"r":{"a":0,"k":0,"ix":10},"p":{"a":0,"k":[180.521,381.44,0],"ix":2,"l":2},"a":{"a":0,"k":[102.521,75.44,0],"ix":1,"l":2},"s":{"a":1,"k":[{"i":{"x":[0.667,0.667,0.667],"y":[1,1,1]},"o":{"x":[0.333,0.333,0.333],"y":[0,0,0]},"t":10,"s":[100,100,100]},{"i":{"x":[0.667,0.667,0.667],"y":[1,1,1]},"o":{"x":[0.333,0.333,0.333],"y":[0,0,0]},"t":17,"s":[120,120,100]},{"t":20,"s":[0,0,100]}],"ix":6,"l":2}},"ao":0,"ef":[{"ty":25,"nm":"Drop Shadow","np":8,"mn":"ADBE Drop Shadow","ix":1,"en":1,"ef":[{"ty":2,"nm":"Shadow Color","mn":"ADBE Drop Shadow-0001","ix":1,"v":{"a":0,"k":[0,0,0,1],"ix":1}},{"ty":0,"nm":"Opacity","mn":"ADBE Drop Shadow-0002","ix":2,"v":{"a":0,"k":255,"ix":2}},{"ty":0,"nm":"Direction","mn":"ADBE Drop Shadow-0003","ix":3,"v":{"a":0,"k":135,"ix":3}},{"ty":0,"nm":"Distance","mn":"ADBE Drop Shadow-0004","ix":4,"v":{"a":0,"k":5,"ix":4}},{"ty":0,"nm":"Softness","mn":"ADBE Drop Shadow-0005","ix":5,"v":{"a":0,"k":23,"ix":5}},{"ty":7,"nm":"Shadow Only","mn":"ADBE Drop Shadow-0006","ix":6,"v":{"a":0,"k":0,"ix":6}}]}],"shapes":[{"ty":"gr","it":[{"ind":0,"ty":"sh","ix":1,"ks":{"a":0,"k":{"i":[[0,0],[0,0],[0,0],[0,0]],"o":[[0,0],[0,0],[0,0],[0,0]],"v":[[2.418,-1.068],[2.418,-10.739],[24.177,-10.739],[24.18,-1.068]],"c":true},"ix":2},"nm":"Path 1","mn":"ADBE Vector Shape - Group","hd":false},{"ind":1,"ty":"sh","ix":2,"ks":{"a":0,"k":{"i":[[0,0],[0,0],[0,0],[0,0]],"o":[[0,0],[0,0],[0,0],[0,0]],"v":[[19.344,27.945],[2.418,27.945],[2.418,3.768],[19.341,3.768]],"c":true},"ix":2},"nm":"Path 2","mn":"ADBE Vector Shape - Group","hd":false},{"ind":2,"ty":"sh","ix":3,"ks":{"a":0,"k":{"i":[[0,0],[0,0],[0,0],[0,0]],"o":[[0,0],[0,0],[0,0],[0,0]],"v":[[-19.341,3.768],[-2.418,3.768],[-2.418,27.945],[-19.341,27.945]],"c":true},"ix":2},"nm":"Path 3","mn":"ADBE Vector Shape - Group","hd":false},{"ind":3,"ty":"sh","ix":4,"ks":{"a":0,"k":{"i":[[0,0],[0,0],[0,0],[0,0]],"o":[[0,0],[0,0],[0,0],[0,0]],"v":[[-24.176,-10.739],[-2.418,-10.739],[-2.418,-1.068],[-24.176,-1.068]],"c":true},"ix":2},"nm":"Path 4","mn":"ADBE Vector Shape - Group","hd":false},{"ind":4,"ty":"sh","ix":5,"ks":{"a":0,"k":{"i":[[-1.603,0],[-1.133,-1.133],[-0.001,-1.602],[0,0],[0,0],[1.134,1.133],[0,1.603],[-1.133,1.134]],"o":[[1.603,0.002],[1.133,1.133],[0,0],[0,0],[-1.603,0],[-1.133,-1.134],[0,-1.603],[1.134,-1.133]],"v":[[-8.462,-27.661],[-4.19,-25.89],[-2.418,-21.618],[-2.418,-15.574],[-8.462,-15.574],[-12.736,-17.344],[-14.506,-21.618],[-12.736,-25.892]],"c":true},"ix":2},"nm":"Path 5","mn":"ADBE Vector Shape - Group","hd":false},{"ind":5,"ty":"sh","ix":6,"ks":{"a":0,"k":{"i":[[0,0],[-0.664,0.994],[-1.105,0.457],[-1.172,-0.233],[-0.846,-0.845],[-0.233,-1.173],[0.457,-1.104],[0.994,-0.664],[1.195,0],[0,0]],"o":[[0,-1.195],[0.665,-0.994],[1.104,-0.457],[1.172,0.233],[0.845,0.845],[0.233,1.172],[-0.458,1.104],[-0.994,0.665],[0,0],[0,0]],"v":[[2.418,-21.618],[3.436,-24.976],[6.149,-27.202],[9.641,-27.546],[12.736,-25.892],[14.39,-22.797],[14.046,-19.305],[11.82,-16.592],[8.462,-15.574],[2.418,-15.574]],"c":true},"ix":2},"nm":"Path 6","mn":"ADBE Vector Shape - Group","hd":false},{"ind":6,"ty":"sh","ix":7,"ks":{"a":0,"k":{"i":[[1.282,0.002],[0,0],[0.482,2.767],[2.267,1.658],[2.782,-0.38],[1.74,-2.204],[2.777,0.374],[2.261,-1.654],[0.485,-2.76],[-1.562,-2.326],[0,0],[0.907,-0.906],[0.002,-1.281],[0,0],[-0.906,-0.906],[-1.282,-0.001],[0,0],[-0.907,-0.907],[-1.282,-0.002],[0,0],[-0.907,0.906],[-0.002,1.281],[0,0],[-0.907,0.907],[-0.002,1.282],[0,0],[0.906,0.907]],"o":[[0,0],[1.573,-2.326],[-0.481,-2.766],[-2.267,-1.658],[-2.783,0.38],[-1.743,-2.193],[-2.777,-0.375],[-2.262,1.654],[-0.485,2.76],[0,0],[-1.282,0.002],[-0.906,0.907],[0,0],[0.002,1.282],[0.907,0.907],[0,0],[0.001,1.281],[0.906,0.906],[0,0],[1.282,-0.002],[0.906,-0.907],[0,0],[1.282,-0.001],[0.906,-0.906],[0,0],[-0.002,-1.281],[-0.907,-0.906]],"v":[[24.177,-15.574],[17.5,-15.574],[19.202,-23.512],[14.919,-30.408],[7.049,-32.4],[0,-28.372],[-7.045,-32.372],[-14.897,-30.379],[-19.178,-23.5],[-17.5,-15.574],[-24.176,-15.574],[-27.594,-14.156],[-29.012,-10.739],[-29.012,-1.068],[-27.594,2.35],[-24.176,3.768],[-24.176,27.945],[-22.758,31.362],[-19.341,32.78],[19.341,32.78],[22.759,31.362],[24.177,27.945],[24.177,3.768],[27.594,2.35],[29.012,-1.068],[29.012,-10.739],[27.594,-14.156]],"c":true},"ix":2},"nm":"Path 7","mn":"ADBE Vector Shape - Group","hd":false},{"ty":"mm","mm":1,"nm":"Merge Paths 1","mn":"ADBE Vector Filter - Merge","hd":false},{"ty":"mm","mm":4,"nm":"Merge Paths 2","mn":"ADBE Vector Filter - Merge","hd":false},{"ty":"fl","c":{"a":0,"k":[1,1,1,1],"ix":4},"o":{"a":0,"k":100,"ix":5},"r":1,"bm":0,"nm":"Fill 1","mn":"ADBE Vector Graphic - Fill","hd":false},{"ty":"tr","p":{"a":0,"k":[102.521,75.3],"ix":2},"a":{"a":0,"k":[0,0],"ix":1},"s":{"a":0,"k":[100,100],"ix":3},"r":{"a":0,"k":0,"ix":6},"o":{"a":0,"k":100,"ix":7},"sk":{"a":0,"k":0,"ix":4},"sa":{"a":0,"k":0,"ix":5},"nm":"Transform"}],"nm":"Group 1","np":10,"cix":2,"bm":0,"ix":1,"mn":"ADBE Vector Group","hd":false}],"ip":0,"op":101,"st":6,"ct":1,"bm":0}],"markers":[],"props":{}}